[
  {
    "platform": "esp32s3-arduino-v3",
    "platform_version": "55.03.36",
    "standard": "c++23",
    "feature": "cpp23/adaptor_iterator_pair_constructor",
    "macro": "__cpp_lib_adaptor_iterator_pair_constructor",
    "category": "library",
    "macro_value": 0,
    "compiles": false,
    "status": "unsupported",
    "compile_time_ms": 391,
    "compiler": "/home/runner/.platformio/tools/toolchain-xtensa-esp-elf/bin/xtensa-esp32s3-elf-g++",
    "timestamp": "2026-04-12T02:34:44.338022",
    "error_output": "src/cpp23__adaptor_iterator_pair_constructor.cpp:10:130: error: no matching function for call to 'std::queue<int>::queue(std::vector<int>::iterator, std::vector<int>::iterator)'\n   10 | auto _test_cpp23__adaptor_iterator_pair_constructor() -> int { std::vector<int> v = {1,2,3}; std::queue<int> q(v.begin(), v.end()); return q.size() == 3 ? 0 : 1; }\n      |                                                                                                                                  ^\nIn file inc",
    "link_failure": false
  },
  {
    "platform": "esp32s3-arduino-v3",
    "platform_version": "55.03.36",
    "standard": "c++23",
    "feature": "cpp23/allocate_at_least",
    "macro": "__cpp_lib_allocate_at_least",
    "category": "library",
    "macro_value": 0,
    "compiles": false,
    "status": "unsupported",
    "compile_time_ms": 391,
    "compiler": "/home/runner/.platformio/tools/toolchain-xtensa-esp-elf/bin/xtensa-esp32s3-elf-g++",
    "timestamp": "2026-04-12T02:34:44.338039",
    "error_output": "src/cpp23__allocate_at_least.cpp:9:89: error: 'class std::allocator<int>' has no member named 'allocate_at_least'\n    9 | auto _test_cpp23__allocate_at_least() -> int { std::allocator<int> a; auto [ptr, n] = a.allocate_at_least(4); a.deallocate(ptr, n); return n >= 4 ? 0 : 1; }\n      |                                                                                         ^~~~~~~~~~~~~~~~~",
    "link_failure": false
  },
  {
    "platform": "esp32s3-arduino-v3",
    "platform_version": "55.03.36",
    "standard": "c++23",
    "feature": "cpp23/associative_heterogeneous_erasure",
    "macro": "__cpp_lib_associative_heterogeneous_erasure",
    "category": "library",
    "macro_value": 0,
    "compiles": false,
    "status": "unsupported",
    "compile_time_ms": 391,
    "compiler": "/home/runner/.platformio/tools/toolchain-xtensa-esp-elf/bin/xtensa-esp32s3-elf-g++",
    "timestamp": "2026-04-12T02:34:44.338045",
    "error_output": "src/cpp23__associative_heterogeneous_erasure.cpp:11:129: error: no matching function for call to 'std::map<std::__cxx11::basic_string<char>, int, std::less<void> >::erase(std::string_view)'\n   11 | auto _test_cpp23__associative_heterogeneous_erasure() -> int { std::map<std::string, int, std::less<>> m; m[\"key\"] = 42; m.erase(std::string_view(\"key\")); return m.empty() ? 0 : 1; }\n      |                                                                                                                ",
    "link_failure": false
  },
  {
    "platform": "esp32s3-arduino-v3",
    "platform_version": "55.03.36",
    "standard": "c++23",
    "feature": "cpp23/atomic_reductions",
    "macro": "__cpp_lib_atomic_reductions",
    "category": "library",
    "macro_value": 0,
    "compiles": true,
    "status": "unreported",
    "compile_time_ms": 391,
    "compiler": "/home/runner/.platformio/tools/toolchain-xtensa-esp-elf/bin/xtensa-esp32s3-elf-g++",
    "timestamp": "2026-04-12T02:34:44.338051",
    "error_output": null,
    "link_failure": false
  },
  {
    "platform": "esp32s3-arduino-v3",
    "platform_version": "55.03.36",
    "standard": "c++23",
    "feature": "cpp23/attr_assume",
    "macro": "__has_cpp_attribute(assume)",
    "category": "attribute",
    "macro_value": 202207,
    "compiles": true,
    "status": "supported",
    "compile_time_ms": 391,
    "compiler": "/home/runner/.platformio/tools/toolchain-xtensa-esp-elf/bin/xtensa-esp32s3-elf-g++",
    "timestamp": "2026-04-12T02:34:44.338057",
    "error_output": null,
    "link_failure": false
  },
  {
    "platform": "esp32s3-arduino-v3",
    "platform_version": "55.03.36",
    "standard": "c++23",
    "feature": "cpp23/attr_carries_dependency",
    "macro": "__has_cpp_attribute(carries_dependency)",
    "category": "attribute",
    "macro_value": 0,
    "compiles": true,
    "status": "unreported",
    "compile_time_ms": 391,
    "compiler": "/home/runner/.platformio/tools/toolchain-xtensa-esp-elf/bin/xtensa-esp32s3-elf-g++",
    "timestamp": "2026-04-12T02:34:44.338062",
    "error_output": null,
    "link_failure": false
  },
  {
    "platform": "esp32s3-arduino-v3",
    "platform_version": "55.03.36",
    "standard": "c++23",
    "feature": "cpp23/attr_deprecated",
    "macro": "__has_cpp_attribute(deprecated)",
    "category": "attribute",
    "macro_value": 201309,
    "compiles": true,
    "status": "supported",
    "compile_time_ms": 391,
    "compiler": "/home/runner/.platformio/tools/toolchain-xtensa-esp-elf/bin/xtensa-esp32s3-elf-g++",
    "timestamp": "2026-04-12T02:34:44.338067",
    "error_output": null,
    "link_failure": false
  },
  {
    "platform": "esp32s3-arduino-v3",
    "platform_version": "55.03.36",
    "standard": "c++23",
    "feature": "cpp23/attr_indeterminate",
    "macro": "__has_cpp_attribute(indeterminate)",
    "category": "attribute",
    "macro_value": 0,
    "compiles": true,
    "status": "unreported",
    "compile_time_ms": 391,
    "compiler": "/home/runner/.platformio/tools/toolchain-xtensa-esp-elf/bin/xtensa-esp32s3-elf-g++",
    "timestamp": "2026-04-12T02:34:44.338071",
    "error_output": null,
    "link_failure": false
  },
  {
    "platform": "esp32s3-arduino-v3",
    "platform_version": "55.03.36",
    "standard": "c++23",
    "feature": "cpp23/attr_no_unique_address",
    "macro": "__has_cpp_attribute(no_unique_address)",
    "category": "attribute",
    "macro_value": 201803,
    "compiles": true,
    "status": "supported",
    "compile_time_ms": 391,
    "compiler": "/home/runner/.platformio/tools/toolchain-xtensa-esp-elf/bin/xtensa-esp32s3-elf-g++",
    "timestamp": "2026-04-12T02:34:44.338076",
    "error_output": null,
    "link_failure": false
  },
  {
    "platform": "esp32s3-arduino-v3",
    "platform_version": "55.03.36",
    "standard": "c++23",
    "feature": "cpp23/attr_nodiscard",
    "macro": "__has_cpp_attribute(nodiscard)",
    "category": "attribute",
    "macro_value": 201907,
    "compiles": true,
    "status": "supported",
    "compile_time_ms": 391,
    "compiler": "/home/runner/.platformio/tools/toolchain-xtensa-esp-elf/bin/xtensa-esp32s3-elf-g++",
    "timestamp": "2026-04-12T02:34:44.338082",
    "error_output": null,
    "link_failure": false
  },
  {
    "platform": "esp32s3-arduino-v3",
    "platform_version": "55.03.36",
    "standard": "c++23",
    "feature": "cpp23/attr_noreturn",
    "macro": "__has_cpp_attribute(noreturn)",
    "category": "attribute",
    "macro_value": 200809,
    "compiles": true,
    "status": "supported",
    "compile_time_ms": 391,
    "compiler": "/home/runner/.platformio/tools/toolchain-xtensa-esp-elf/bin/xtensa-esp32s3-elf-g++",
    "timestamp": "2026-04-12T02:34:44.338086",
    "error_output": null,
    "link_failure": false
  },
  {
    "platform": "esp32s3-arduino-v3",
    "platform_version": "55.03.36",
    "standard": "c++23",
    "feature": "cpp23/auto_cast",
    "macro": "__cpp_auto_cast",
    "category": "language",
    "macro_value": 0,
    "compiles": true,
    "status": "unreported",
    "compile_time_ms": 391,
    "compiler": "/home/runner/.platformio/tools/toolchain-xtensa-esp-elf/bin/xtensa-esp32s3-elf-g++",
    "timestamp": "2026-04-12T02:34:44.338091",
    "error_output": null,
    "link_failure": false
  },
  {
    "platform": "esp32s3-arduino-v3",
    "platform_version": "55.03.36",
    "standard": "c++23",
    "feature": "cpp23/bind_back",
    "macro": "__cpp_lib_bind_back",
    "category": "library",
    "macro_value": 0,
    "compiles": false,
    "status": "unsupported",
    "compile_time_ms": 391,
    "compiler": "/home/runner/.platformio/tools/toolchain-xtensa-esp-elf/bin/xtensa-esp32s3-elf-g++",
    "timestamp": "2026-04-12T02:34:44.338095",
    "error_output": "src/cpp23__bind_back.cpp:10:57: error: 'bind_back' is not a member of 'std'\n   10 | auto _test_cpp23__bind_back() -> int { auto sub5 = std::bind_back(sub, 5); return sub5(8) - 3; }\n      |                                                         ^~~~~~~~~",
    "link_failure": false
  },
  {
    "platform": "esp32s3-arduino-v3",
    "platform_version": "55.03.36",
    "standard": "c++23",
    "feature": "cpp23/byteswap",
    "macro": "__cpp_lib_byteswap",
    "category": "library",
    "macro_value": 0,
    "compiles": false,
    "status": "unsupported",
    "compile_time_ms": 391,
    "compiler": "/home/runner/.platformio/tools/toolchain-xtensa-esp-elf/bin/xtensa-esp32s3-elf-g++",
    "timestamp": "2026-04-12T02:34:44.338100",
    "error_output": "src/cpp23__byteswap.cpp:11:29: error: 'byteswap' is not a member of 'std'\n   11 |     uint16_t swapped = std::byteswap(val);\n      |                             ^~~~~~~~",
    "link_failure": false
  },
  {
    "platform": "esp32s3-arduino-v3",
    "platform_version": "55.03.36",
    "standard": "c++23",
    "feature": "cpp23/constexpr_atomic",
    "macro": "__cpp_lib_constexpr_atomic",
    "category": "library",
    "macro_value": 0,
    "compiles": true,
    "status": "unreported",
    "compile_time_ms": 391,
    "compiler": "/home/runner/.platformio/tools/toolchain-xtensa-esp-elf/bin/xtensa-esp32s3-elf-g++",
    "timestamp": "2026-04-12T02:34:44.338105",
    "error_output": null,
    "link_failure": false
  },
  {
    "platform": "esp32s3-arduino-v3",
    "platform_version": "55.03.36",
    "standard": "c++23",
    "feature": "cpp23/constexpr_bitset",
    "macro": "__cpp_lib_constexpr_bitset",
    "category": "library",
    "macro_value": 0,
    "compiles": false,
    "status": "unsupported",
    "compile_time_ms": 391,
    "compiler": "/home/runner/.platformio/tools/toolchain-xtensa-esp-elf/bin/xtensa-esp32s3-elf-g++",
    "timestamp": "2026-04-12T02:34:44.338109",
    "error_output": "src/cpp23__constexpr_bitset.cpp:10:25: error: non-constant condition for static assertion\n   10 | static_assert(b.count() == 4);\n      |               ~~~~~~~~~~^~~~\nsrc/cpp23__constexpr_bitset.cpp:10:22: error: call to non-'constexpr' function 'std::size_t std::bitset<_Nb>::count() const [with unsigned int _Nb = 8; std::size_t = unsigned int]'\n   10 | static_assert(b.count() == 4);\n      |               ~~~~~~~^~\nIn file included from src/cpp23__constexpr_bitset.cpp:8:",
    "link_failure": false
  },
  {
    "platform": "esp32s3-arduino-v3",
    "platform_version": "55.03.36",
    "standard": "c++23",
    "feature": "cpp23/constexpr_charconv",
    "macro": "__cpp_lib_constexpr_charconv",
    "category": "library",
    "macro_value": 0,
    "compiles": false,
    "status": "unsupported",
    "compile_time_ms": 391,
    "compiler": "/home/runner/.platformio/tools/toolchain-xtensa-esp-elf/bin/xtensa-esp32s3-elf-g++",
    "timestamp": "2026-04-12T02:34:44.338113",
    "error_output": "src/cpp23__constexpr_charconv.cpp:10:79: warning: call to non-'constexpr' function 'std::to_chars_result std::to_chars(char*, char*, int, int)' [-Winvalid-constexpr]\n   10 | constexpr int f() { std::array<char, 16> buf{}; auto [ptr, ec] = std::to_chars(buf.data(), buf.data() + buf.size(), 42); return ec == std::errc{} ? 0 : 1; }\n      |                                                                  ~~~~~~~~~~~~~^~~~~~~~~~~~~~~~~~~~~~~~~~~~~~~~~~~~~~~~~\nIn file included from src/cpp23__constexp",
    "link_failure": false
  },
  {
    "platform": "esp32s3-arduino-v3",
    "platform_version": "55.03.36",
    "standard": "c++23",
    "feature": "cpp23/constexpr_cmath",
    "macro": "__cpp_lib_constexpr_cmath",
    "category": "library",
    "macro_value": 0,
    "compiles": true,
    "status": "unreported",
    "compile_time_ms": 391,
    "compiler": "/home/runner/.platformio/tools/toolchain-xtensa-esp-elf/bin/xtensa-esp32s3-elf-g++",
    "timestamp": "2026-04-12T02:34:44.338118",
    "error_output": null,
    "link_failure": false
  },
  {
    "platform": "esp32s3-arduino-v3",
    "platform_version": "55.03.36",
    "standard": "c++23",
    "feature": "cpp23/constexpr_deque",
    "macro": "__cpp_lib_constexpr_deque",
    "category": "library",
    "macro_value": 0,
    "compiles": true,
    "status": "unreported",
    "compile_time_ms": 391,
    "compiler": "/home/runner/.platformio/tools/toolchain-xtensa-esp-elf/bin/xtensa-esp32s3-elf-g++",
    "timestamp": "2026-04-12T02:34:44.338122",
    "error_output": null,
    "link_failure": false
  },
  {
    "platform": "esp32s3-arduino-v3",
    "platform_version": "55.03.36",
    "standard": "c++23",
    "feature": "cpp23/constexpr_format",
    "macro": "__cpp_lib_constexpr_format",
    "category": "library",
    "macro_value": 0,
    "compiles": true,
    "status": "unreported",
    "compile_time_ms": 391,
    "compiler": "/home/runner/.platformio/tools/toolchain-xtensa-esp-elf/bin/xtensa-esp32s3-elf-g++",
    "timestamp": "2026-04-12T02:34:44.338126",
    "error_output": null,
    "link_failure": false
  },
  {
    "platform": "esp32s3-arduino-v3",
    "platform_version": "55.03.36",
    "standard": "c++23",
    "feature": "cpp23/constexpr_inplace_vector",
    "macro": "__cpp_lib_constexpr_inplace_vector",
    "category": "library",
    "macro_value": 0,
    "compiles": false,
    "status": "unsupported",
    "compile_time_ms": 391,
    "compiler": "/home/runner/.platformio/tools/toolchain-xtensa-esp-elf/bin/xtensa-esp32s3-elf-g++",
    "timestamp": "2026-04-12T02:34:44.338130",
    "error_output": "src/cpp23__constexpr_inplace_vector.cpp:8:10: fatal error: inplace_vector: No such file or directory\n    8 | #include <inplace_vector>\n      |          ^~~~~~~~~~~~~~~~",
    "link_failure": false
  },
  {
    "platform": "esp32s3-arduino-v3",
    "platform_version": "55.03.36",
    "standard": "c++23",
    "feature": "cpp23/constexpr_map",
    "macro": "__cpp_lib_constexpr_map",
    "category": "library",
    "macro_value": 0,
    "compiles": true,
    "status": "unreported",
    "compile_time_ms": 391,
    "compiler": "/home/runner/.platformio/tools/toolchain-xtensa-esp-elf/bin/xtensa-esp32s3-elf-g++",
    "timestamp": "2026-04-12T02:34:44.338134",
    "error_output": null,
    "link_failure": false
  },
  {
    "platform": "esp32s3-arduino-v3",
    "platform_version": "55.03.36",
    "standard": "c++23",
    "feature": "cpp23/constexpr_set",
    "macro": "__cpp_lib_constexpr_set",
    "category": "library",
    "macro_value": 0,
    "compiles": true,
    "status": "unreported",
    "compile_time_ms": 391,
    "compiler": "/home/runner/.platformio/tools/toolchain-xtensa-esp-elf/bin/xtensa-esp32s3-elf-g++",
    "timestamp": "2026-04-12T02:34:44.338139",
    "error_output": null,
    "link_failure": false
  },
  {
    "platform": "esp32s3-arduino-v3",
    "platform_version": "55.03.36",
    "standard": "c++23",
    "feature": "cpp23/constexpr_stack",
    "macro": "__cpp_lib_constexpr_stack",
    "category": "library",
    "macro_value": 0,
    "compiles": true,
    "status": "unreported",
    "compile_time_ms": 391,
    "compiler": "/home/runner/.platformio/tools/toolchain-xtensa-esp-elf/bin/xtensa-esp32s3-elf-g++",
    "timestamp": "2026-04-12T02:34:44.338143",
    "error_output": null,
    "link_failure": false
  },
  {
    "platform": "esp32s3-arduino-v3",
    "platform_version": "55.03.36",
    "standard": "c++23",
    "feature": "cpp23/constexpr_typeinfo",
    "macro": "__cpp_lib_constexpr_typeinfo",
    "category": "library",
    "macro_value": 0,
    "compiles": false,
    "status": "unsupported",
    "compile_time_ms": 391,
    "compiler": "/home/runner/.platformio/tools/toolchain-xtensa-esp-elf/bin/xtensa-esp32s3-elf-g++",
    "timestamp": "2026-04-12T02:34:44.338147",
    "error_output": "src/cpp23__constexpr_typeinfo.cpp:9:80: error: cannot use 'typeid' with '-fno-rtti'\n    9 | auto _test_cpp23__constexpr_typeinfo() -> int { constexpr auto& ti = typeid(int); return ti == typeid(int) ? 0 : 1; }\n      |                                                                                ^\nsrc/cpp23__constexpr_typeinfo.cpp:9:106: error: cannot use 'typeid' with '-fno-rtti'\n    9 | auto _test_cpp23__constexpr_typeinfo() -> int { constexpr auto& ti = typeid(int); return ti == typeid(int) ?",
    "link_failure": false
  },
  {
    "platform": "esp32s3-arduino-v3",
    "platform_version": "55.03.36",
    "standard": "c++23",
    "feature": "cpp23/constexpr_unordered_map",
    "macro": "__cpp_lib_constexpr_unordered_map",
    "category": "library",
    "macro_value": 0,
    "compiles": true,
    "status": "unreported",
    "compile_time_ms": 391,
    "compiler": "/home/runner/.platformio/tools/toolchain-xtensa-esp-elf/bin/xtensa-esp32s3-elf-g++",
    "timestamp": "2026-04-12T02:34:44.338151",
    "error_output": null,
    "link_failure": false
  },
  {
    "platform": "esp32s3-arduino-v3",
    "platform_version": "55.03.36",
    "standard": "c++23",
    "feature": "cpp23/constexpr_unordered_set",
    "macro": "__cpp_lib_constexpr_unordered_set",
    "category": "library",
    "macro_value": 0,
    "compiles": true,
    "status": "unreported",
    "compile_time_ms": 391,
    "compiler": "/home/runner/.platformio/tools/toolchain-xtensa-esp-elf/bin/xtensa-esp32s3-elf-g++",
    "timestamp": "2026-04-12T02:34:44.338156",
    "error_output": null,
    "link_failure": false
  },
  {
    "platform": "esp32s3-arduino-v3",
    "platform_version": "55.03.36",
    "standard": "c++23",
    "feature": "cpp23/containers_ranges",
    "macro": "__cpp_lib_containers_ranges",
    "category": "library",
    "macro_value": 0,
    "compiles": true,
    "status": "unreported",
    "compile_time_ms": 391,
    "compiler": "/home/runner/.platformio/tools/toolchain-xtensa-esp-elf/bin/xtensa-esp32s3-elf-g++",
    "timestamp": "2026-04-12T02:34:44.338160",
    "error_output": null,
    "link_failure": false
  },
  {
    "platform": "esp32s3-arduino-v3",
    "platform_version": "55.03.36",
    "standard": "c++23",
    "feature": "cpp23/counting_scope",
    "macro": "__cpp_lib_counting_scope",
    "category": "library",
    "macro_value": 0,
    "compiles": true,
    "status": "unreported",
    "compile_time_ms": 391,
    "compiler": "/home/runner/.platformio/tools/toolchain-xtensa-esp-elf/bin/xtensa-esp32s3-elf-g++",
    "timestamp": "2026-04-12T02:34:44.338164",
    "error_output": null,
    "link_failure": false
  },
  {
    "platform": "esp32s3-arduino-v3",
    "platform_version": "55.03.36",
    "standard": "c++23",
    "feature": "cpp23/deduction_guides",
    "macro": "__cpp_lib_deduction_guides",
    "category": "library",
    "macro_value": 0,
    "compiles": true,
    "status": "unreported",
    "compile_time_ms": 391,
    "compiler": "/home/runner/.platformio/tools/toolchain-xtensa-esp-elf/bin/xtensa-esp32s3-elf-g++",
    "timestamp": "2026-04-12T02:34:44.338168",
    "error_output": null,
    "link_failure": false
  },
  {
    "platform": "esp32s3-arduino-v3",
    "platform_version": "55.03.36",
    "standard": "c++23",
    "feature": "cpp23/expected",
    "macro": "__cpp_lib_expected",
    "category": "library",
    "macro_value": 0,
    "compiles": false,
    "status": "unsupported",
    "compile_time_ms": 391,
    "compiler": "/home/runner/.platformio/tools/toolchain-xtensa-esp-elf/bin/xtensa-esp32s3-elf-g++",
    "timestamp": "2026-04-12T02:34:44.338172",
    "error_output": "src/cpp23__expected.cpp:10:35: error: 'expected' in namespace 'std' does not name a template type\n   10 | auto divide(int a, int b) -> std::expected<int, const char*> {\n      |                                   ^~~~~~~~\n   10 | auto divide(int a, int b) -> std::expected<int, const char*> {\n      |                              ^~~\nsrc/cpp23__expected.cpp:10:43: error: expected initializer before '<' token\n   10 | auto divide(int a, int b) -> std::expected<int, const char*> {\n      |              ",
    "link_failure": false
  },
  {
    "platform": "esp32s3-arduino-v3",
    "platform_version": "55.03.36",
    "standard": "c++23",
    "feature": "cpp23/explicit_this_parameter",
    "macro": "__cpp_explicit_this_parameter",
    "category": "language",
    "macro_value": 0,
    "compiles": true,
    "status": "unreported",
    "compile_time_ms": 391,
    "compiler": "/home/runner/.platformio/tools/toolchain-xtensa-esp-elf/bin/xtensa-esp32s3-elf-g++",
    "timestamp": "2026-04-12T02:34:44.338177",
    "error_output": null,
    "link_failure": false
  },
  {
    "platform": "esp32s3-arduino-v3",
    "platform_version": "55.03.36",
    "standard": "c++23",
    "feature": "cpp23/flat_map",
    "macro": "__cpp_lib_flat_map",
    "category": "library",
    "macro_value": 0,
    "compiles": false,
    "status": "unsupported",
    "compile_time_ms": 391,
    "compiler": "/home/runner/.platformio/tools/toolchain-xtensa-esp-elf/bin/xtensa-esp32s3-elf-g++",
    "timestamp": "2026-04-12T02:34:44.338181",
    "error_output": "src/cpp23__flat_map.cpp:8:10: fatal error: flat_map: No such file or directory\n    8 | #include <flat_map>\n      |          ^~~~~~~~~~",
    "link_failure": false
  },
  {
    "platform": "esp32s3-arduino-v3",
    "platform_version": "55.03.36",
    "standard": "c++23",
    "feature": "cpp23/flat_set",
    "macro": "__cpp_lib_flat_set",
    "category": "library",
    "macro_value": 0,
    "compiles": false,
    "status": "unsupported",
    "compile_time_ms": 391,
    "compiler": "/home/runner/.platformio/tools/toolchain-xtensa-esp-elf/bin/xtensa-esp32s3-elf-g++",
    "timestamp": "2026-04-12T02:34:44.338185",
    "error_output": "src/cpp23__flat_set.cpp:8:10: fatal error: flat_set: No such file or directory\n    8 | #include <flat_set>\n      |          ^~~~~~~~~~",
    "link_failure": false
  },
  {
    "platform": "esp32s3-arduino-v3",
    "platform_version": "55.03.36",
    "standard": "c++23",
    "feature": "cpp23/format_ranges",
    "macro": "__cpp_lib_format_ranges",
    "category": "library",
    "macro_value": 0,
    "compiles": false,
    "status": "unsupported",
    "compile_time_ms": 391,
    "compiler": "/home/runner/.platformio/tools/toolchain-xtensa-esp-elf/bin/xtensa-esp32s3-elf-g++",
    "timestamp": "2026-04-12T02:34:44.338190",
    "error_output": "In file included from src/cpp23__format_ranges.cpp:8:\n   10 | auto _test_cpp23__format_ranges() -> int { std::vector<int> v = {1, 2, 3}; auto s = std::format(\"{}\", v); return s.empty() ? 1 : 0; }\n      |                                                                                     ~~~~~~~~~~~^~~~~~~~~\n/home/runner/.platformio/packages/toolchain-xtensa-esp-elf/xtensa-esp-elf/include/c++/14.2.0/format:4062:10: error: static assertion failed: std::formatter must be specialized for each type b",
    "link_failure": false
  },
  {
    "platform": "esp32s3-arduino-v3",
    "platform_version": "55.03.36",
    "standard": "c++23",
    "feature": "cpp23/formatters",
    "macro": "__cpp_lib_formatters",
    "category": "library",
    "macro_value": 0,
    "compiles": false,
    "status": "unsupported",
    "compile_time_ms": 391,
    "compiler": "/home/runner/.platformio/tools/toolchain-xtensa-esp-elf/bin/xtensa-esp32s3-elf-g++",
    "timestamp": "2026-04-12T02:34:44.338194",
    "error_output": "In file included from src/cpp23__formatters.cpp:8:\n   10 | auto _test_cpp23__formatters() -> int { auto s = std::format(\"{}\", std::this_thread::get_id()); return s.empty() ? 1 : 0; }\n      |                                                  ~~~~~~~~~~~^~~~~~~~~~~~~~~~~~~~~~~~~~~~~~~~~~\n/home/runner/.platformio/packages/toolchain-xtensa-esp-elf/xtensa-esp-elf/include/c++/14.2.0/format:4062:10: error: static assertion failed: std::formatter must be specialized for each type being formatted\n 4062 | ",
    "link_failure": false
  },
  {
    "platform": "esp32s3-arduino-v3",
    "platform_version": "55.03.36",
    "standard": "c++23",
    "feature": "cpp23/forward_like",
    "macro": "__cpp_lib_forward_like",
    "category": "library",
    "macro_value": 0,
    "compiles": false,
    "status": "unsupported",
    "compile_time_ms": 391,
    "compiler": "/home/runner/.platformio/tools/toolchain-xtensa-esp-elf/bin/xtensa-esp32s3-elf-g++",
    "timestamp": "2026-04-12T02:34:44.338198",
    "error_output": "src/cpp23__forward_like.cpp:12:23: error: 'forward_like' is not a member of 'std'\n   12 |     auto&& ref = std::forward_like<const S&>(s.x);\n      |                       ^~~~~~~~~~~~\nsrc/cpp23__forward_like.cpp:12:36: error: expected primary-expression before 'const'\n   12 |     auto&& ref = std::forward_like<const S&>(s.x);\n      |                                    ^~~~~",
    "link_failure": false
  },
  {
    "platform": "esp32s3-arduino-v3",
    "platform_version": "55.03.36",
    "standard": "c++23",
    "feature": "cpp23/freestanding_algorithm",
    "macro": "__cpp_lib_freestanding_algorithm",
    "category": "library",
    "macro_value": 0,
    "compiles": true,
    "status": "unreported",
    "compile_time_ms": 391,
    "compiler": "/home/runner/.platformio/tools/toolchain-xtensa-esp-elf/bin/xtensa-esp32s3-elf-g++",
    "timestamp": "2026-04-12T02:34:44.338202",
    "error_output": null,
    "link_failure": false
  },
  {
    "platform": "esp32s3-arduino-v3",
    "platform_version": "55.03.36",
    "standard": "c++23",
    "feature": "cpp23/freestanding_array",
    "macro": "__cpp_lib_freestanding_array",
    "category": "library",
    "macro_value": 0,
    "compiles": true,
    "status": "unreported",
    "compile_time_ms": 391,
    "compiler": "/home/runner/.platformio/tools/toolchain-xtensa-esp-elf/bin/xtensa-esp32s3-elf-g++",
    "timestamp": "2026-04-12T02:34:44.338207",
    "error_output": null,
    "link_failure": false
  },
  {
    "platform": "esp32s3-arduino-v3",
    "platform_version": "55.03.36",
    "standard": "c++23",
    "feature": "cpp23/freestanding_char_traits",
    "macro": "__cpp_lib_freestanding_char_traits",
    "category": "library",
    "macro_value": 0,
    "compiles": true,
    "status": "unreported",
    "compile_time_ms": 391,
    "compiler": "/home/runner/.platformio/tools/toolchain-xtensa-esp-elf/bin/xtensa-esp32s3-elf-g++",
    "timestamp": "2026-04-12T02:34:44.338210",
    "error_output": null,
    "link_failure": false
  },
  {
    "platform": "esp32s3-arduino-v3",
    "platform_version": "55.03.36",
    "standard": "c++23",
    "feature": "cpp23/freestanding_cstdlib",
    "macro": "__cpp_lib_freestanding_cstdlib",
    "category": "library",
    "macro_value": 0,
    "compiles": true,
    "status": "unreported",
    "compile_time_ms": 391,
    "compiler": "/home/runner/.platformio/tools/toolchain-xtensa-esp-elf/bin/xtensa-esp32s3-elf-g++",
    "timestamp": "2026-04-12T02:34:44.338215",
    "error_output": null,
    "link_failure": false
  },
  {
    "platform": "esp32s3-arduino-v3",
    "platform_version": "55.03.36",
    "standard": "c++23",
    "feature": "cpp23/freestanding_cstring",
    "macro": "__cpp_lib_freestanding_cstring",
    "category": "library",
    "macro_value": 0,
    "compiles": true,
    "status": "unreported",
    "compile_time_ms": 391,
    "compiler": "/home/runner/.platformio/tools/toolchain-xtensa-esp-elf/bin/xtensa-esp32s3-elf-g++",
    "timestamp": "2026-04-12T02:34:44.338219",
    "error_output": null,
    "link_failure": false
  },
  {
    "platform": "esp32s3-arduino-v3",
    "platform_version": "55.03.36",
    "standard": "c++23",
    "feature": "cpp23/freestanding_cwchar",
    "macro": "__cpp_lib_freestanding_cwchar",
    "category": "library",
    "macro_value": 0,
    "compiles": true,
    "status": "unreported",
    "compile_time_ms": 391,
    "compiler": "/home/runner/.platformio/tools/toolchain-xtensa-esp-elf/bin/xtensa-esp32s3-elf-g++",
    "timestamp": "2026-04-12T02:34:44.338223",
    "error_output": null,
    "link_failure": false
  },
  {
    "platform": "esp32s3-arduino-v3",
    "platform_version": "55.03.36",
    "standard": "c++23",
    "feature": "cpp23/freestanding_errc",
    "macro": "__cpp_lib_freestanding_errc",
    "category": "library",
    "macro_value": 0,
    "compiles": true,
    "status": "unreported",
    "compile_time_ms": 391,
    "compiler": "/home/runner/.platformio/tools/toolchain-xtensa-esp-elf/bin/xtensa-esp32s3-elf-g++",
    "timestamp": "2026-04-12T02:34:44.338227",
    "error_output": null,
    "link_failure": false
  },
  {
    "platform": "esp32s3-arduino-v3",
    "platform_version": "55.03.36",
    "standard": "c++23",
    "feature": "cpp23/freestanding_execution",
    "macro": "__cpp_lib_freestanding_execution",
    "category": "library",
    "macro_value": 0,
    "compiles": true,
    "status": "unreported",
    "compile_time_ms": 391,
    "compiler": "/home/runner/.platformio/tools/toolchain-xtensa-esp-elf/bin/xtensa-esp32s3-elf-g++",
    "timestamp": "2026-04-12T02:34:44.338231",
    "error_output": null,
    "link_failure": false
  },
  {
    "platform": "esp32s3-arduino-v3",
    "platform_version": "55.03.36",
    "standard": "c++23",
    "feature": "cpp23/freestanding_expected",
    "macro": "__cpp_lib_freestanding_expected",
    "category": "library",
    "macro_value": 0,
    "compiles": true,
    "status": "unreported",
    "compile_time_ms": 391,
    "compiler": "/home/runner/.platformio/tools/toolchain-xtensa-esp-elf/bin/xtensa-esp32s3-elf-g++",
    "timestamp": "2026-04-12T02:34:44.338235",
    "error_output": null,
    "link_failure": false
  },
  {
    "platform": "esp32s3-arduino-v3",
    "platform_version": "55.03.36",
    "standard": "c++23",
    "feature": "cpp23/freestanding_feature_test_macros",
    "macro": "__cpp_lib_freestanding_feature_test_macros",
    "category": "library",
    "macro_value": 0,
    "compiles": true,
    "status": "unreported",
    "compile_time_ms": 391,
    "compiler": "/home/runner/.platformio/tools/toolchain-xtensa-esp-elf/bin/xtensa-esp32s3-elf-g++",
    "timestamp": "2026-04-12T02:34:44.338239",
    "error_output": null,
    "link_failure": false
  },
  {
    "platform": "esp32s3-arduino-v3",
    "platform_version": "55.03.36",
    "standard": "c++23",
    "feature": "cpp23/freestanding_functional",
    "macro": "__cpp_lib_freestanding_functional",
    "category": "library",
    "macro_value": 0,
    "compiles": true,
    "status": "unreported",
    "compile_time_ms": 391,
    "compiler": "/home/runner/.platformio/tools/toolchain-xtensa-esp-elf/bin/xtensa-esp32s3-elf-g++",
    "timestamp": "2026-04-12T02:34:44.338243",
    "error_output": null,
    "link_failure": false
  },
  {
    "platform": "esp32s3-arduino-v3",
    "platform_version": "55.03.36",
    "standard": "c++23",
    "feature": "cpp23/freestanding_iterator",
    "macro": "__cpp_lib_freestanding_iterator",
    "category": "library",
    "macro_value": 0,
    "compiles": true,
    "status": "unreported",
    "compile_time_ms": 391,
    "compiler": "/home/runner/.platformio/tools/toolchain-xtensa-esp-elf/bin/xtensa-esp32s3-elf-g++",
    "timestamp": "2026-04-12T02:34:44.338247",
    "error_output": null,
    "link_failure": false
  },
  {
    "platform": "esp32s3-arduino-v3",
    "platform_version": "55.03.36",
    "standard": "c++23",
    "feature": "cpp23/freestanding_mdspan",
    "macro": "__cpp_lib_freestanding_mdspan",
    "category": "library",
    "macro_value": 0,
    "compiles": false,
    "status": "unsupported",
    "compile_time_ms": 391,
    "compiler": "/home/runner/.platformio/tools/toolchain-xtensa-esp-elf/bin/xtensa-esp32s3-elf-g++",
    "timestamp": "2026-04-12T02:34:44.338251",
    "error_output": "src/cpp23__freestanding_mdspan.cpp:8:10: fatal error: mdspan: No such file or directory\n    8 | #include <mdspan>\n      |          ^~~~~~~~",
    "link_failure": false
  },
  {
    "platform": "esp32s3-arduino-v3",
    "platform_version": "55.03.36",
    "standard": "c++23",
    "feature": "cpp23/freestanding_memory",
    "macro": "__cpp_lib_freestanding_memory",
    "category": "library",
    "macro_value": 0,
    "compiles": true,
    "status": "unreported",
    "compile_time_ms": 391,
    "compiler": "/home/runner/.platformio/tools/toolchain-xtensa-esp-elf/bin/xtensa-esp32s3-elf-g++",
    "timestamp": "2026-04-12T02:34:44.338255",
    "error_output": null,
    "link_failure": false
  },
  {
    "platform": "esp32s3-arduino-v3",
    "platform_version": "55.03.36",
    "standard": "c++23",
    "feature": "cpp23/freestanding_numeric",
    "macro": "__cpp_lib_freestanding_numeric",
    "category": "library",
    "macro_value": 0,
    "compiles": true,
    "status": "unreported",
    "compile_time_ms": 391,
    "compiler": "/home/runner/.platformio/tools/toolchain-xtensa-esp-elf/bin/xtensa-esp32s3-elf-g++",
    "timestamp": "2026-04-12T02:34:44.338259",
    "error_output": null,
    "link_failure": false
  },
  {
    "platform": "esp32s3-arduino-v3",
    "platform_version": "55.03.36",
    "standard": "c++23",
    "feature": "cpp23/freestanding_operator_new",
    "macro": "__cpp_lib_freestanding_operator_new",
    "category": "library",
    "macro_value": 0,
    "compiles": true,
    "status": "unreported",
    "compile_time_ms": 391,
    "compiler": "/home/runner/.platformio/tools/toolchain-xtensa-esp-elf/bin/xtensa-esp32s3-elf-g++",
    "timestamp": "2026-04-12T02:34:44.338263",
    "error_output": null,
    "link_failure": false
  },
  {
    "platform": "esp32s3-arduino-v3",
    "platform_version": "55.03.36",
    "standard": "c++23",
    "feature": "cpp23/freestanding_optional",
    "macro": "__cpp_lib_freestanding_optional",
    "category": "library",
    "macro_value": 0,
    "compiles": true,
    "status": "unreported",
    "compile_time_ms": 391,
    "compiler": "/home/runner/.platformio/tools/toolchain-xtensa-esp-elf/bin/xtensa-esp32s3-elf-g++",
    "timestamp": "2026-04-12T02:34:44.338267",
    "error_output": null,
    "link_failure": false
  },
  {
    "platform": "esp32s3-arduino-v3",
    "platform_version": "55.03.36",
    "standard": "c++23",
    "feature": "cpp23/freestanding_random",
    "macro": "__cpp_lib_freestanding_random",
    "category": "library",
    "macro_value": 0,
    "compiles": true,
    "status": "unreported",
    "compile_time_ms": 391,
    "compiler": "/home/runner/.platformio/tools/toolchain-xtensa-esp-elf/bin/xtensa-esp32s3-elf-g++",
    "timestamp": "2026-04-12T02:34:44.338271",
    "error_output": null,
    "link_failure": false
  },
  {
    "platform": "esp32s3-arduino-v3",
    "platform_version": "55.03.36",
    "standard": "c++23",
    "feature": "cpp23/freestanding_ratio",
    "macro": "__cpp_lib_freestanding_ratio",
    "category": "library",
    "macro_value": 0,
    "compiles": true,
    "status": "unreported",
    "compile_time_ms": 391,
    "compiler": "/home/runner/.platformio/tools/toolchain-xtensa-esp-elf/bin/xtensa-esp32s3-elf-g++",
    "timestamp": "2026-04-12T02:34:44.338275",
    "error_output": null,
    "link_failure": false
  },
  {
    "platform": "esp32s3-arduino-v3",
    "platform_version": "55.03.36",
    "standard": "c++23",
    "feature": "cpp23/freestanding_string_view",
    "macro": "__cpp_lib_freestanding_string_view",
    "category": "library",
    "macro_value": 0,
    "compiles": true,
    "status": "unreported",
    "compile_time_ms": 391,
    "compiler": "/home/runner/.platformio/tools/toolchain-xtensa-esp-elf/bin/xtensa-esp32s3-elf-g++",
    "timestamp": "2026-04-12T02:34:44.338279",
    "error_output": null,
    "link_failure": false
  },
  {
    "platform": "esp32s3-arduino-v3",
    "platform_version": "55.03.36",
    "standard": "c++23",
    "feature": "cpp23/freestanding_tuple",
    "macro": "__cpp_lib_freestanding_tuple",
    "category": "library",
    "macro_value": 0,
    "compiles": true,
    "status": "unreported",
    "compile_time_ms": 391,
    "compiler": "/home/runner/.platformio/tools/toolchain-xtensa-esp-elf/bin/xtensa-esp32s3-elf-g++",
    "timestamp": "2026-04-12T02:34:44.338283",
    "error_output": null,
    "link_failure": false
  },
  {
    "platform": "esp32s3-arduino-v3",
    "platform_version": "55.03.36",
    "standard": "c++23",
    "feature": "cpp23/freestanding_utility",
    "macro": "__cpp_lib_freestanding_utility",
    "category": "library",
    "macro_value": 0,
    "compiles": true,
    "status": "unreported",
    "compile_time_ms": 391,
    "compiler": "/home/runner/.platformio/tools/toolchain-xtensa-esp-elf/bin/xtensa-esp32s3-elf-g++",
    "timestamp": "2026-04-12T02:34:44.338287",
    "error_output": null,
    "link_failure": false
  },
  {
    "platform": "esp32s3-arduino-v3",
    "platform_version": "55.03.36",
    "standard": "c++23",
    "feature": "cpp23/freestanding_variant",
    "macro": "__cpp_lib_freestanding_variant",
    "category": "library",
    "macro_value": 0,
    "compiles": true,
    "status": "unreported",
    "compile_time_ms": 391,
    "compiler": "/home/runner/.platformio/tools/toolchain-xtensa-esp-elf/bin/xtensa-esp32s3-elf-g++",
    "timestamp": "2026-04-12T02:34:44.338291",
    "error_output": null,
    "link_failure": false
  },
  {
    "platform": "esp32s3-arduino-v3",
    "platform_version": "55.03.36",
    "standard": "c++23",
    "feature": "cpp23/generator",
    "macro": "__cpp_lib_generator",
    "category": "library",
    "macro_value": 0,
    "compiles": false,
    "status": "unsupported",
    "compile_time_ms": 391,
    "compiler": "/home/runner/.platformio/tools/toolchain-xtensa-esp-elf/bin/xtensa-esp32s3-elf-g++",
    "timestamp": "2026-04-12T02:34:44.338294",
    "error_output": "src/cpp23__generator.cpp:10:6: error: 'generator' in namespace 'std' does not name a template type; did you mean 'generate'?\n   10 | std::generator<int> iota(int n) { for (int i=0; i<n; ++i) co_yield i; }\n      |      ^~~~~~~~~\n      |      generate\nsrc/cpp23__generator.cpp:11:63: error: 'iota' was not declared in this scope; did you mean 'std::ranges::views::iota'?\n   11 | auto _test_cpp23__generator() -> int { int s=0; for (auto i : iota(4)) s+=i; return s-6; }\n      |                         ",
    "link_failure": false
  },
  {
    "platform": "esp32s3-arduino-v3",
    "platform_version": "55.03.36",
    "standard": "c++23",
    "feature": "cpp23/hardened_array",
    "macro": "__cpp_lib_hardened_array",
    "category": "library",
    "macro_value": 0,
    "compiles": true,
    "status": "unreported",
    "compile_time_ms": 391,
    "compiler": "/home/runner/.platformio/tools/toolchain-xtensa-esp-elf/bin/xtensa-esp32s3-elf-g++",
    "timestamp": "2026-04-12T02:34:44.338299",
    "error_output": null,
    "link_failure": false
  },
  {
    "platform": "esp32s3-arduino-v3",
    "platform_version": "55.03.36",
    "standard": "c++23",
    "feature": "cpp23/hardened_basic_stacktrace",
    "macro": "__cpp_lib_hardened_basic_stacktrace",
    "category": "library",
    "macro_value": 0,
    "compiles": true,
    "status": "unreported",
    "compile_time_ms": 391,
    "compiler": "/home/runner/.platformio/tools/toolchain-xtensa-esp-elf/bin/xtensa-esp32s3-elf-g++",
    "timestamp": "2026-04-12T02:34:44.338302",
    "error_output": null,
    "link_failure": false
  },
  {
    "platform": "esp32s3-arduino-v3",
    "platform_version": "55.03.36",
    "standard": "c++23",
    "feature": "cpp23/hardened_basic_string",
    "macro": "__cpp_lib_hardened_basic_string",
    "category": "library",
    "macro_value": 0,
    "compiles": true,
    "status": "unreported",
    "compile_time_ms": 391,
    "compiler": "/home/runner/.platformio/tools/toolchain-xtensa-esp-elf/bin/xtensa-esp32s3-elf-g++",
    "timestamp": "2026-04-12T02:34:44.338306",
    "error_output": null,
    "link_failure": false
  },
  {
    "platform": "esp32s3-arduino-v3",
    "platform_version": "55.03.36",
    "standard": "c++23",
    "feature": "cpp23/hardened_basic_string_view",
    "macro": "__cpp_lib_hardened_basic_string_view",
    "category": "library",
    "macro_value": 0,
    "compiles": true,
    "status": "unreported",
    "compile_time_ms": 391,
    "compiler": "/home/runner/.platformio/tools/toolchain-xtensa-esp-elf/bin/xtensa-esp32s3-elf-g++",
    "timestamp": "2026-04-12T02:34:44.338310",
    "error_output": null,
    "link_failure": false
  },
  {
    "platform": "esp32s3-arduino-v3",
    "platform_version": "55.03.36",
    "standard": "c++23",
    "feature": "cpp23/hardened_bitset",
    "macro": "__cpp_lib_hardened_bitset",
    "category": "library",
    "macro_value": 0,
    "compiles": true,
    "status": "unreported",
    "compile_time_ms": 391,
    "compiler": "/home/runner/.platformio/tools/toolchain-xtensa-esp-elf/bin/xtensa-esp32s3-elf-g++",
    "timestamp": "2026-04-12T02:34:44.338314",
    "error_output": null,
    "link_failure": false
  },
  {
    "platform": "esp32s3-arduino-v3",
    "platform_version": "55.03.36",
    "standard": "c++23",
    "feature": "cpp23/hardened_common_iterator",
    "macro": "__cpp_lib_hardened_common_iterator",
    "category": "library",
    "macro_value": 0,
    "compiles": true,
    "status": "unreported",
    "compile_time_ms": 391,
    "compiler": "/home/runner/.platformio/tools/toolchain-xtensa-esp-elf/bin/xtensa-esp32s3-elf-g++",
    "timestamp": "2026-04-12T02:34:44.338318",
    "error_output": null,
    "link_failure": false
  },
  {
    "platform": "esp32s3-arduino-v3",
    "platform_version": "55.03.36",
    "standard": "c++23",
    "feature": "cpp23/hardened_counted_iterator",
    "macro": "__cpp_lib_hardened_counted_iterator",
    "category": "library",
    "macro_value": 0,
    "compiles": true,
    "status": "unreported",
    "compile_time_ms": 391,
    "compiler": "/home/runner/.platformio/tools/toolchain-xtensa-esp-elf/bin/xtensa-esp32s3-elf-g++",
    "timestamp": "2026-04-12T02:34:44.338322",
    "error_output": null,
    "link_failure": false
  },
  {
    "platform": "esp32s3-arduino-v3",
    "platform_version": "55.03.36",
    "standard": "c++23",
    "feature": "cpp23/hardened_deque",
    "macro": "__cpp_lib_hardened_deque",
    "category": "library",
    "macro_value": 0,
    "compiles": true,
    "status": "unreported",
    "compile_time_ms": 391,
    "compiler": "/home/runner/.platformio/tools/toolchain-xtensa-esp-elf/bin/xtensa-esp32s3-elf-g++",
    "timestamp": "2026-04-12T02:34:44.338326",
    "error_output": null,
    "link_failure": false
  },
  {
    "platform": "esp32s3-arduino-v3",
    "platform_version": "55.03.36",
    "standard": "c++23",
    "feature": "cpp23/hardened_expected",
    "macro": "__cpp_lib_hardened_expected",
    "category": "library",
    "macro_value": 0,
    "compiles": true,
    "status": "unreported",
    "compile_time_ms": 391,
    "compiler": "/home/runner/.platformio/tools/toolchain-xtensa-esp-elf/bin/xtensa-esp32s3-elf-g++",
    "timestamp": "2026-04-12T02:34:44.338330",
    "error_output": null,
    "link_failure": false
  },
  {
    "platform": "esp32s3-arduino-v3",
    "platform_version": "55.03.36",
    "standard": "c++23",
    "feature": "cpp23/hardened_forward_list",
    "macro": "__cpp_lib_hardened_forward_list",
    "category": "library",
    "macro_value": 0,
    "compiles": true,
    "status": "unreported",
    "compile_time_ms": 391,
    "compiler": "/home/runner/.platformio/tools/toolchain-xtensa-esp-elf/bin/xtensa-esp32s3-elf-g++",
    "timestamp": "2026-04-12T02:34:44.338335",
    "error_output": null,
    "link_failure": false
  },
  {
    "platform": "esp32s3-arduino-v3",
    "platform_version": "55.03.36",
    "standard": "c++23",
    "feature": "cpp23/hardened_inplace_vector",
    "macro": "__cpp_lib_hardened_inplace_vector",
    "category": "library",
    "macro_value": 0,
    "compiles": false,
    "status": "unsupported",
    "compile_time_ms": 391,
    "compiler": "/home/runner/.platformio/tools/toolchain-xtensa-esp-elf/bin/xtensa-esp32s3-elf-g++",
    "timestamp": "2026-04-12T02:34:44.338339",
    "error_output": "src/cpp23__hardened_inplace_vector.cpp:8:10: fatal error: inplace_vector: No such file or directory\n    8 | #include <inplace_vector>\n      |          ^~~~~~~~~~~~~~~~",
    "link_failure": false
  },
  {
    "platform": "esp32s3-arduino-v3",
    "platform_version": "55.03.36",
    "standard": "c++23",
    "feature": "cpp23/hardened_list",
    "macro": "__cpp_lib_hardened_list",
    "category": "library",
    "macro_value": 0,
    "compiles": true,
    "status": "unreported",
    "compile_time_ms": 391,
    "compiler": "/home/runner/.platformio/tools/toolchain-xtensa-esp-elf/bin/xtensa-esp32s3-elf-g++",
    "timestamp": "2026-04-12T02:34:44.338343",
    "error_output": null,
    "link_failure": false
  },
  {
    "platform": "esp32s3-arduino-v3",
    "platform_version": "55.03.36",
    "standard": "c++23",
    "feature": "cpp23/hardened_mdspan",
    "macro": "__cpp_lib_hardened_mdspan",
    "category": "library",
    "macro_value": 0,
    "compiles": false,
    "status": "unsupported",
    "compile_time_ms": 391,
    "compiler": "/home/runner/.platformio/tools/toolchain-xtensa-esp-elf/bin/xtensa-esp32s3-elf-g++",
    "timestamp": "2026-04-12T02:34:44.338347",
    "error_output": "src/cpp23__hardened_mdspan.cpp:8:10: fatal error: mdspan: No such file or directory\n    8 | #include <mdspan>\n      |          ^~~~~~~~",
    "link_failure": false
  },
  {
    "platform": "esp32s3-arduino-v3",
    "platform_version": "55.03.36",
    "standard": "c++23",
    "feature": "cpp23/hardened_optional",
    "macro": "__cpp_lib_hardened_optional",
    "category": "library",
    "macro_value": 0,
    "compiles": true,
    "status": "unreported",
    "compile_time_ms": 391,
    "compiler": "/home/runner/.platformio/tools/toolchain-xtensa-esp-elf/bin/xtensa-esp32s3-elf-g++",
    "timestamp": "2026-04-12T02:34:44.338351",
    "error_output": null,
    "link_failure": false
  },
  {
    "platform": "esp32s3-arduino-v3",
    "platform_version": "55.03.36",
    "standard": "c++23",
    "feature": "cpp23/hardened_shared_ptr_array",
    "macro": "__cpp_lib_hardened_shared_ptr_array",
    "category": "library",
    "macro_value": 0,
    "compiles": true,
    "status": "unreported",
    "compile_time_ms": 391,
    "compiler": "/home/runner/.platformio/tools/toolchain-xtensa-esp-elf/bin/xtensa-esp32s3-elf-g++",
    "timestamp": "2026-04-12T02:34:44.338355",
    "error_output": null,
    "link_failure": false
  },
  {
    "platform": "esp32s3-arduino-v3",
    "platform_version": "55.03.36",
    "standard": "c++23",
    "feature": "cpp23/hardened_span",
    "macro": "__cpp_lib_hardened_span",
    "category": "library",
    "macro_value": 0,
    "compiles": true,
    "status": "unreported",
    "compile_time_ms": 391,
    "compiler": "/home/runner/.platformio/tools/toolchain-xtensa-esp-elf/bin/xtensa-esp32s3-elf-g++",
    "timestamp": "2026-04-12T02:34:44.338360",
    "error_output": null,
    "link_failure": false
  },
  {
    "platform": "esp32s3-arduino-v3",
    "platform_version": "55.03.36",
    "standard": "c++23",
    "feature": "cpp23/hardened_valarray",
    "macro": "__cpp_lib_hardened_valarray",
    "category": "library",
    "macro_value": 0,
    "compiles": true,
    "status": "unreported",
    "compile_time_ms": 391,
    "compiler": "/home/runner/.platformio/tools/toolchain-xtensa-esp-elf/bin/xtensa-esp32s3-elf-g++",
    "timestamp": "2026-04-12T02:34:44.338364",
    "error_output": null,
    "link_failure": false
  },
  {
    "platform": "esp32s3-arduino-v3",
    "platform_version": "55.03.36",
    "standard": "c++23",
    "feature": "cpp23/hardened_vector",
    "macro": "__cpp_lib_hardened_vector",
    "category": "library",
    "macro_value": 0,
    "compiles": true,
    "status": "unreported",
    "compile_time_ms": 391,
    "compiler": "/home/runner/.platformio/tools/toolchain-xtensa-esp-elf/bin/xtensa-esp32s3-elf-g++",
    "timestamp": "2026-04-12T02:34:44.338368",
    "error_output": null,
    "link_failure": false
  },
  {
    "platform": "esp32s3-arduino-v3",
    "platform_version": "55.03.36",
    "standard": "c++23",
    "feature": "cpp23/hardened_view_interface",
    "macro": "__cpp_lib_hardened_view_interface",
    "category": "library",
    "macro_value": 0,
    "compiles": true,
    "status": "unreported",
    "compile_time_ms": 391,
    "compiler": "/home/runner/.platformio/tools/toolchain-xtensa-esp-elf/bin/xtensa-esp32s3-elf-g++",
    "timestamp": "2026-04-12T02:34:44.338372",
    "error_output": null,
    "link_failure": false
  },
  {
    "platform": "esp32s3-arduino-v3",
    "platform_version": "55.03.36",
    "standard": "c++23",
    "feature": "cpp23/hazard_pointer",
    "macro": "__cpp_lib_hazard_pointer",
    "category": "library",
    "macro_value": 0,
    "compiles": false,
    "status": "unsupported",
    "compile_time_ms": 391,
    "compiler": "/home/runner/.platformio/tools/toolchain-xtensa-esp-elf/bin/xtensa-esp32s3-elf-g++",
    "timestamp": "2026-04-12T02:34:44.338376",
    "error_output": "src/cpp23__hazard_pointer.cpp:8:10: fatal error: hazard_pointer: No such file or directory\n    8 | #include <hazard_pointer>\n      |          ^~~~~~~~~~~~~~~~",
    "link_failure": false
  },
  {
    "platform": "esp32s3-arduino-v3",
    "platform_version": "55.03.36",
    "standard": "c++23",
    "feature": "cpp23/hive",
    "macro": "__cpp_lib_hive",
    "category": "library",
    "macro_value": 0,
    "compiles": false,
    "status": "unsupported",
    "compile_time_ms": 391,
    "compiler": "/home/runner/.platformio/tools/toolchain-xtensa-esp-elf/bin/xtensa-esp32s3-elf-g++",
    "timestamp": "2026-04-12T02:34:44.338381",
    "error_output": "src/cpp23__hive.cpp:8:10: fatal error: hive: No such file or directory\n    8 | #include <hive>\n      |          ^~~~~~",
    "link_failure": false
  },
  {
    "platform": "esp32s3-arduino-v3",
    "platform_version": "55.03.36",
    "standard": "c++23",
    "feature": "cpp23/if_consteval",
    "macro": "__cpp_if_consteval",
    "category": "language",
    "macro_value": 0,
    "compiles": true,
    "status": "unreported",
    "compile_time_ms": 391,
    "compiler": "/home/runner/.platformio/tools/toolchain-xtensa-esp-elf/bin/xtensa-esp32s3-elf-g++",
    "timestamp": "2026-04-12T02:34:44.338385",
    "error_output": null,
    "link_failure": false
  },
  {
    "platform": "esp32s3-arduino-v3",
    "platform_version": "55.03.36",
    "standard": "c++23",
    "feature": "cpp23/implicit_move",
    "macro": "__cpp_implicit_move",
    "category": "language",
    "macro_value": 0,
    "compiles": true,
    "status": "unreported",
    "compile_time_ms": 391,
    "compiler": "/home/runner/.platformio/tools/toolchain-xtensa-esp-elf/bin/xtensa-esp32s3-elf-g++",
    "timestamp": "2026-04-12T02:34:44.338388",
    "error_output": null,
    "link_failure": false
  },
  {
    "platform": "esp32s3-arduino-v3",
    "platform_version": "55.03.36",
    "standard": "c++23",
    "feature": "cpp23/initializer_list_lib",
    "macro": "__cpp_lib_initializer_list",
    "category": "library",
    "macro_value": 0,
    "compiles": true,
    "status": "unreported",
    "compile_time_ms": 391,
    "compiler": "/home/runner/.platformio/tools/toolchain-xtensa-esp-elf/bin/xtensa-esp32s3-elf-g++",
    "timestamp": "2026-04-12T02:34:44.338392",
    "error_output": null,
    "link_failure": false
  },
  {
    "platform": "esp32s3-arduino-v3",
    "platform_version": "55.03.36",
    "standard": "c++23",
    "feature": "cpp23/invoke_r",
    "macro": "__cpp_lib_invoke_r",
    "category": "library",
    "macro_value": 0,
    "compiles": false,
    "status": "unsupported",
    "compile_time_ms": 391,
    "compiler": "/home/runner/.platformio/tools/toolchain-xtensa-esp-elf/bin/xtensa-esp32s3-elf-g++",
    "timestamp": "2026-04-12T02:34:44.338396",
    "error_output": "src/cpp23__invoke_r.cpp:10:51: error: 'invoke_r' is not a member of 'std'\n   10 | auto _test_cpp23__invoke_r() -> int { return std::invoke_r<long>(add, 2, 3) - 5; }\n      |                                                   ^~~~~~~~\nsrc/cpp23__invoke_r.cpp:10:60: error: expected primary-expression before 'long'\n   10 | auto _test_cpp23__invoke_r() -> int { return std::invoke_r<long>(add, 2, 3) - 5; }\n      |                                                            ^~~~\nsrc/cpp23__invoke_r.cpp:1",
    "link_failure": false
  },
  {
    "platform": "esp32s3-arduino-v3",
    "platform_version": "55.03.36",
    "standard": "c++23",
    "feature": "cpp23/ios_noreplace",
    "macro": "__cpp_lib_ios_noreplace",
    "category": "library",
    "macro_value": 0,
    "compiles": false,
    "status": "unsupported",
    "compile_time_ms": 391,
    "compiler": "/home/runner/.platformio/tools/toolchain-xtensa-esp-elf/bin/xtensa-esp32s3-elf-g++",
    "timestamp": "2026-04-12T02:34:44.338400",
    "error_output": "src/cpp23__ios_noreplace.cpp:9:66: error: 'noreplace' is not a member of 'std::ios' {aka 'std::basic_ios<char>'}\n    9 | auto _test_cpp23__ios_noreplace() -> int { auto mode = std::ios::noreplace; (void)mode; return 0; }\n      |                                                                  ^~~~~~~~~",
    "link_failure": false
  },
  {
    "platform": "esp32s3-arduino-v3",
    "platform_version": "55.03.36",
    "standard": "c++23",
    "feature": "cpp23/is_implicit_lifetime",
    "macro": "__cpp_lib_is_implicit_lifetime",
    "category": "library",
    "macro_value": 0,
    "compiles": false,
    "status": "unsupported",
    "compile_time_ms": 391,
    "compiler": "/home/runner/.platformio/tools/toolchain-xtensa-esp-elf/bin/xtensa-esp32s3-elf-g++",
    "timestamp": "2026-04-12T02:34:44.338404",
    "error_output": "src/cpp23__is_implicit_lifetime.cpp:10:63: error: 'is_implicit_lifetime_v' is not a member of 'std'\n   10 | auto _test_cpp23__is_implicit_lifetime() -> int { return std::is_implicit_lifetime_v<S> ? 0 : 1; }\n      |                                                               ^~~~~~~~~~~~~~~~~~~~~~\nsrc/cpp23__is_implicit_lifetime.cpp:10:87: error: expected primary-expression before '>' token\n   10 | auto _test_cpp23__is_implicit_lifetime() -> int { return std::is_implicit_lifetime_v<S> ? 0 : 1; ",
    "link_failure": false
  },
  {
    "platform": "esp32s3-arduino-v3",
    "platform_version": "55.03.36",
    "standard": "c++23",
    "feature": "cpp23/is_layout_compatible",
    "macro": "__cpp_lib_is_layout_compatible",
    "category": "library",
    "macro_value": 201907,
    "compiles": true,
    "status": "supported",
    "compile_time_ms": 391,
    "compiler": "/home/runner/.platformio/tools/toolchain-xtensa-esp-elf/bin/xtensa-esp32s3-elf-g++",
    "timestamp": "2026-04-12T02:34:44.338408",
    "error_output": null,
    "link_failure": false
  },
  {
    "platform": "esp32s3-arduino-v3",
    "platform_version": "55.03.36",
    "standard": "c++23",
    "feature": "cpp23/is_pointer_interconvertible",
    "macro": "__cpp_lib_is_pointer_interconvertible",
    "category": "library",
    "macro_value": 201907,
    "compiles": true,
    "status": "supported",
    "compile_time_ms": 391,
    "compiler": "/home/runner/.platformio/tools/toolchain-xtensa-esp-elf/bin/xtensa-esp32s3-elf-g++",
    "timestamp": "2026-04-12T02:34:44.338413",
    "error_output": null,
    "link_failure": false
  },
  {
    "platform": "esp32s3-arduino-v3",
    "platform_version": "55.03.36",
    "standard": "c++23",
    "feature": "cpp23/is_scoped_enum",
    "macro": "__cpp_lib_is_scoped_enum",
    "category": "library",
    "macro_value": 0,
    "compiles": false,
    "status": "unsupported",
    "compile_time_ms": 391,
    "compiler": "/home/runner/.platformio/tools/toolchain-xtensa-esp-elf/bin/xtensa-esp32s3-elf-g++",
    "timestamp": "2026-04-12T02:34:44.338417",
    "error_output": "src/cpp23__is_scoped_enum.cpp:10:57: error: 'is_scoped_enum_v' is not a member of 'std'\n   10 | auto _test_cpp23__is_scoped_enum() -> int { return std::is_scoped_enum_v<B> && !std::is_scoped_enum_v<A> ? 0 : 1; }\n      |                                                         ^~~~~~~~~~~~~~~~\nsrc/cpp23__is_scoped_enum.cpp:10:75: error: expected primary-expression before '>' token\n   10 | auto _test_cpp23__is_scoped_enum() -> int { return std::is_scoped_enum_v<B> && !std::is_scoped_enum_v<A> ? 0 :",
    "link_failure": false
  },
  {
    "platform": "esp32s3-arduino-v3",
    "platform_version": "55.03.36",
    "standard": "c++23",
    "feature": "cpp23/linalg",
    "macro": "__cpp_lib_linalg",
    "category": "library",
    "macro_value": 0,
    "compiles": false,
    "status": "unsupported",
    "compile_time_ms": 391,
    "compiler": "/home/runner/.platformio/tools/toolchain-xtensa-esp-elf/bin/xtensa-esp32s3-elf-g++",
    "timestamp": "2026-04-12T02:34:44.338421",
    "error_output": "src/cpp23__linalg.cpp:8:10: fatal error: linalg: No such file or directory\n    8 | #include <linalg>\n      |          ^~~~~~~~",
    "link_failure": false
  },
  {
    "platform": "esp32s3-arduino-v3",
    "platform_version": "55.03.36",
    "standard": "c++23",
    "feature": "cpp23/mdspan",
    "macro": "__cpp_lib_mdspan",
    "category": "library",
    "macro_value": 0,
    "compiles": false,
    "status": "unsupported",
    "compile_time_ms": 391,
    "compiler": "/home/runner/.platformio/tools/toolchain-xtensa-esp-elf/bin/xtensa-esp32s3-elf-g++",
    "timestamp": "2026-04-12T02:34:44.338425",
    "error_output": "src/cpp23__mdspan.cpp:8:10: fatal error: mdspan: No such file or directory\n    8 | #include <mdspan>\n      |          ^~~~~~~~",
    "link_failure": false
  },
  {
    "platform": "esp32s3-arduino-v3",
    "platform_version": "55.03.36",
    "standard": "c++23",
    "feature": "cpp23/move_only_function",
    "macro": "__cpp_lib_move_only_function",
    "category": "library",
    "macro_value": 0,
    "compiles": false,
    "status": "unsupported",
    "compile_time_ms": 391,
    "compiler": "/home/runner/.platformio/tools/toolchain-xtensa-esp-elf/bin/xtensa-esp32s3-elf-g++",
    "timestamp": "2026-04-12T02:34:44.338429",
    "error_output": "src/cpp23__move_only_function.cpp:9:54: error: 'move_only_function' is not a member of 'std'\n    9 | auto _test_cpp23__move_only_function() -> int { std::move_only_function<int()> f = []{ return 42; }; return f() - 42; }\n      |                                                      ^~~~~~~~~~~~~~~~~~\nsrc/cpp23__move_only_function.cpp:9:80: error: 'f' was not declared in this scope\n    9 | auto _test_cpp23__move_only_function() -> int { std::move_only_function<int()> f = []{ return 42; }; return f",
    "link_failure": false
  },
  {
    "platform": "esp32s3-arduino-v3",
    "platform_version": "55.03.36",
    "standard": "c++23",
    "feature": "cpp23/multidimensional_subscript",
    "macro": "__cpp_multidimensional_subscript",
    "category": "language",
    "macro_value": 0,
    "compiles": false,
    "status": "unsupported",
    "compile_time_ms": 391,
    "compiler": "/home/runner/.platformio/tools/toolchain-xtensa-esp-elf/bin/xtensa-esp32s3-elf-g++",
    "timestamp": "2026-04-12T02:34:44.338433",
    "error_output": "src/cpp23__multidimensional_subscript.cpp:10:9: error: 'int Matrix::operator[](int, int)' must have exactly one argument\n   10 |     int operator[](int r, int c) { return data[r * 2 + c]; }\n      |         ^~~~~~~~\nsrc/cpp23__multidimensional_subscript.cpp:15:15: warning: top-level comma expression in array subscript is deprecated [-Wcomma-subscript]\n   15 |     return m[1, 1] - 3;\n      |               ^\nsrc/cpp23__multidimensional_subscript.cpp:15:13: error: no match for 'operator[]' (operand ",
    "link_failure": false
  },
  {
    "platform": "esp32s3-arduino-v3",
    "platform_version": "55.03.36",
    "standard": "c++23",
    "feature": "cpp23/named_character_escapes",
    "macro": "__cpp_named_character_escapes",
    "category": "language",
    "macro_value": 0,
    "compiles": true,
    "status": "unreported",
    "compile_time_ms": 391,
    "compiler": "/home/runner/.platformio/tools/toolchain-xtensa-esp-elf/bin/xtensa-esp32s3-elf-g++",
    "timestamp": "2026-04-12T02:34:44.338437",
    "error_output": null,
    "link_failure": false
  },
  {
    "platform": "esp32s3-arduino-v3",
    "platform_version": "55.03.36",
    "standard": "c++23",
    "feature": "cpp23/out_ptr",
    "macro": "__cpp_lib_out_ptr",
    "category": "library",
    "macro_value": 0,
    "compiles": false,
    "status": "unsupported",
    "compile_time_ms": 391,
    "compiler": "/home/runner/.platformio/tools/toolchain-xtensa-esp-elf/bin/xtensa-esp32s3-elf-g++",
    "timestamp": "2026-04-12T02:34:44.338441",
    "error_output": "src/cpp23__out_ptr.cpp:10:78: error: 'out_ptr' is not a member of 'std'; did you mean 'auto_ptr'?\n   10 | auto _test_cpp23__out_ptr() -> int { std::unique_ptr<int> up; alloc_int(std::out_ptr(up)); return *up - 42; }\n      |                                                                              ^~~~~~~\n      |                                                                              auto_ptr",
    "link_failure": false
  },
  {
    "platform": "esp32s3-arduino-v3",
    "platform_version": "55.03.36",
    "standard": "c++23",
    "feature": "cpp23/parallel_scheduler",
    "macro": "__cpp_lib_parallel_scheduler",
    "category": "library",
    "macro_value": 0,
    "compiles": true,
    "status": "unreported",
    "compile_time_ms": 391,
    "compiler": "/home/runner/.platformio/tools/toolchain-xtensa-esp-elf/bin/xtensa-esp32s3-elf-g++",
    "timestamp": "2026-04-12T02:34:44.338446",
    "error_output": null,
    "link_failure": false
  },
  {
    "platform": "esp32s3-arduino-v3",
    "platform_version": "55.03.36",
    "standard": "c++23",
    "feature": "cpp23/print",
    "macro": "__cpp_lib_print",
    "category": "library",
    "macro_value": 0,
    "compiles": false,
    "status": "unsupported",
    "compile_time_ms": 391,
    "compiler": "/home/runner/.platformio/tools/toolchain-xtensa-esp-elf/bin/xtensa-esp32s3-elf-g++",
    "timestamp": "2026-04-12T02:34:44.338450",
    "error_output": "src/cpp23__print.cpp:10:10: error: 'println' is not a member of 'std'; did you mean 'rintl'?\n   10 |     std::println(\"hello\");\n      |          ^~~~~~~\n      |          rintl",
    "link_failure": false
  },
  {
    "platform": "esp32s3-arduino-v3",
    "platform_version": "55.03.36",
    "standard": "c++23",
    "feature": "cpp23/ranges_as_const",
    "macro": "__cpp_lib_ranges_as_const",
    "category": "library",
    "macro_value": 0,
    "compiles": false,
    "status": "unsupported",
    "compile_time_ms": 391,
    "compiler": "/home/runner/.platformio/tools/toolchain-xtensa-esp-elf/bin/xtensa-esp32s3-elf-g++",
    "timestamp": "2026-04-12T02:34:44.338454",
    "error_output": "src/cpp23__ranges_as_const.cpp:10:102: error: 'as_const' is not a member of 'std::views'\n   10 | auto _test_cpp23__ranges_as_const() -> int { std::vector<int> v = {1,2,3}; auto cv = v | std::views::as_const; return *cv.begin() == 1 ? 0 : 1; }\n      |                                                                                                      ^~~~~~~~",
    "link_failure": false
  },
  {
    "platform": "esp32s3-arduino-v3",
    "platform_version": "55.03.36",
    "standard": "c++23",
    "feature": "cpp23/ranges_as_rvalue",
    "macro": "__cpp_lib_ranges_as_rvalue",
    "category": "library",
    "macro_value": 0,
    "compiles": false,
    "status": "unsupported",
    "compile_time_ms": 391,
    "compiler": "/home/runner/.platformio/tools/toolchain-xtensa-esp-elf/bin/xtensa-esp32s3-elf-g++",
    "timestamp": "2026-04-12T02:34:44.338457",
    "error_output": "src/cpp23__ranges_as_rvalue.cpp:10:102: error: 'as_rvalue' is not a member of 'std::views'\n   10 | auto _test_cpp23__ranges_as_rvalue() -> int { std::vector<int> v = {1,2,3}; auto r = v | std::views::as_rvalue; int s = 0; for (auto x : r) s += x; return s - 6; }\n      |                                                                                                      ^~~~~~~~~",
    "link_failure": false
  },
  {
    "platform": "esp32s3-arduino-v3",
    "platform_version": "55.03.36",
    "standard": "c++23",
    "feature": "cpp23/ranges_cartesian_product",
    "macro": "__cpp_lib_ranges_cartesian_product",
    "category": "library",
    "macro_value": 0,
    "compiles": false,
    "status": "unsupported",
    "compile_time_ms": 391,
    "compiler": "/home/runner/.platformio/tools/toolchain-xtensa-esp-elf/bin/xtensa-esp32s3-elf-g++",
    "timestamp": "2026-04-12T02:34:44.338461",
    "error_output": "src/cpp23__ranges_cartesian_product.cpp:10:142: error: 'cartesian_product' is not a member of 'std::views'\n   10 | auto _test_cpp23__ranges_cartesian_product() -> int { std::vector a = {1,2}; std::vector b = {3,4}; int n = 0; for (auto [x,y] : std::views::cartesian_product(a, b)) n++; return n == 4 ? 0 : 1; }\n      |                                                                                                                                              ^~~~~~~~~~~~~~~~~",
    "link_failure": false
  },
  {
    "platform": "esp32s3-arduino-v3",
    "platform_version": "55.03.36",
    "standard": "c++23",
    "feature": "cpp23/ranges_chunk",
    "macro": "__cpp_lib_ranges_chunk",
    "category": "library",
    "macro_value": 0,
    "compiles": false,
    "status": "unsupported",
    "compile_time_ms": 391,
    "compiler": "/home/runner/.platformio/tools/toolchain-xtensa-esp-elf/bin/xtensa-esp32s3-elf-g++",
    "timestamp": "2026-04-12T02:34:44.338465",
    "error_output": "src/cpp23__ranges_chunk.cpp:10:111: error: 'chunk' is not a member of 'std::views'\n   10 | auto _test_cpp23__ranges_chunk() -> int { std::vector v = {1,2,3,4}; int n = 0; for (auto c : v | std::views::chunk(2)) n++; return n == 2 ? 0 : 1; }\n      |                                                                                                               ^~~~~",
    "link_failure": false
  },
  {
    "platform": "esp32s3-arduino-v3",
    "platform_version": "55.03.36",
    "standard": "c++23",
    "feature": "cpp23/ranges_chunk_by",
    "macro": "__cpp_lib_ranges_chunk_by",
    "category": "library",
    "macro_value": 0,
    "compiles": false,
    "status": "unsupported",
    "compile_time_ms": 391,
    "compiler": "/home/runner/.platformio/tools/toolchain-xtensa-esp-elf/bin/xtensa-esp32s3-elf-g++",
    "timestamp": "2026-04-12T02:34:44.338469",
    "error_output": "src/cpp23__ranges_chunk_by.cpp:10:116: error: 'chunk_by' is not a member of 'std::views'\n   10 | auto _test_cpp23__ranges_chunk_by() -> int { std::vector v = {1,1,2,2,3}; int n = 0; for (auto c : v | std::views::chunk_by(std::equal_to<>{})) n++; return n == 3 ? 0 : 1; }\n      |                                                                                                                    ^~~~~~~~",
    "link_failure": false
  },
  {
    "platform": "esp32s3-arduino-v3",
    "platform_version": "55.03.36",
    "standard": "c++23",
    "feature": "cpp23/ranges_contains",
    "macro": "__cpp_lib_ranges_contains",
    "category": "library",
    "macro_value": 0,
    "compiles": false,
    "status": "unsupported",
    "compile_time_ms": 391,
    "compiler": "/home/runner/.platformio/tools/toolchain-xtensa-esp-elf/bin/xtensa-esp32s3-elf-g++",
    "timestamp": "2026-04-12T02:34:44.338473",
    "error_output": "src/cpp23__ranges_contains.cpp:10:91: error: 'contains' is not a member of 'std::ranges'\n   10 | auto _test_cpp23__ranges_contains() -> int { std::vector v = {1,2,3}; return std::ranges::contains(v, 2) ? 0 : 1; }\n      |                                                                                           ^~~~~~~~",
    "link_failure": false
  },
  {
    "platform": "esp32s3-arduino-v3",
    "platform_version": "55.03.36",
    "standard": "c++23",
    "feature": "cpp23/ranges_enumerate",
    "macro": "__cpp_lib_ranges_enumerate",
    "category": "library",
    "macro_value": 0,
    "compiles": false,
    "status": "unsupported",
    "compile_time_ms": 391,
    "compiler": "/home/runner/.platformio/tools/toolchain-xtensa-esp-elf/bin/xtensa-esp32s3-elf-g++",
    "timestamp": "2026-04-12T02:34:44.338477",
    "error_output": "src/cpp23__ranges_enumerate.cpp:10:117: error: 'enumerate' is not a member of 'std::views'\n   10 | auto _test_cpp23__ranges_enumerate() -> int { std::vector v = {10,20,30}; int s = 0; for (auto [i, x] : std::views::enumerate(v)) s += i; return s == 3 ? 0 : 1; }\n      |                                                                                                                     ^~~~~~~~~",
    "link_failure": false
  },
  {
    "platform": "esp32s3-arduino-v3",
    "platform_version": "55.03.36",
    "standard": "c++23",
    "feature": "cpp23/ranges_find_last",
    "macro": "__cpp_lib_ranges_find_last",
    "category": "library",
    "macro_value": 0,
    "compiles": false,
    "status": "unsupported",
    "compile_time_ms": 391,
    "compiler": "/home/runner/.platformio/tools/toolchain-xtensa-esp-elf/bin/xtensa-esp32s3-elf-g++",
    "timestamp": "2026-04-12T02:34:44.338481",
    "error_output": "src/cpp23__ranges_find_last.cpp:10:98: error: 'find_last' is not a member of 'std::ranges'\n   10 | auto _test_cpp23__ranges_find_last() -> int { std::vector v = {1,2,3,2,1}; auto r = std::ranges::find_last(v, 2); return *r.begin() == 2 && r.begin() == v.begin()+3 ? 0 : 1; }\n      |                                                                                                  ^~~~~~~~~",
    "link_failure": false
  },
  {
    "platform": "esp32s3-arduino-v3",
    "platform_version": "55.03.36",
    "standard": "c++23",
    "feature": "cpp23/ranges_fold",
    "macro": "__cpp_lib_ranges_fold",
    "category": "library",
    "macro_value": 0,
    "compiles": false,
    "status": "unsupported",
    "compile_time_ms": 391,
    "compiler": "/home/runner/.platformio/tools/toolchain-xtensa-esp-elf/bin/xtensa-esp32s3-elf-g++",
    "timestamp": "2026-04-12T02:34:44.338485",
    "error_output": "src/cpp23__ranges_fold.cpp:11:87: error: 'fold_left' is not a member of 'std::ranges'\n   11 | auto _test_cpp23__ranges_fold() -> int { std::vector v = {1,2,3}; return std::ranges::fold_left(v, 0, std::plus{}) - 6; }\n      |                                                                                       ^~~~~~~~~",
    "link_failure": false
  },
  {
    "platform": "esp32s3-arduino-v3",
    "platform_version": "55.03.36",
    "standard": "c++23",
    "feature": "cpp23/ranges_generate_random",
    "macro": "__cpp_lib_ranges_generate_random",
    "category": "library",
    "macro_value": 0,
    "compiles": true,
    "status": "unreported",
    "compile_time_ms": 391,
    "compiler": "/home/runner/.platformio/tools/toolchain-xtensa-esp-elf/bin/xtensa-esp32s3-elf-g++",
    "timestamp": "2026-04-12T02:34:44.338489",
    "error_output": null,
    "link_failure": false
  },
  {
    "platform": "esp32s3-arduino-v3",
    "platform_version": "55.03.36",
    "standard": "c++23",
    "feature": "cpp23/ranges_iota",
    "macro": "__cpp_lib_ranges_iota",
    "category": "library",
    "macro_value": 0,
    "compiles": false,
    "status": "unsupported",
    "compile_time_ms": 391,
    "compiler": "/home/runner/.platformio/tools/toolchain-xtensa-esp-elf/bin/xtensa-esp32s3-elf-g++",
    "timestamp": "2026-04-12T02:34:44.338493",
    "error_output": "src/cpp23__ranges_iota.cpp:10:78: error: 'iota' is not a member of 'std::ranges'; did you mean 'std::iota'?\n   10 | auto _test_cpp23__ranges_iota() -> int { std::vector<int> v(5); std::ranges::iota(v, 1); return v[0] == 1 && v[4] == 5 ? 0 : 1; }\n      |                                                                              ^~~~\nIn file included from /home/runner/.platformio/packages/toolchain-xtensa-esp-elf/xtensa-esp-elf/include/c++/14.2.0/numeric:62,\n                 from src/cpp23__rang",
    "link_failure": false
  },
  {
    "platform": "esp32s3-arduino-v3",
    "platform_version": "55.03.36",
    "standard": "c++23",
    "feature": "cpp23/ranges_join_with",
    "macro": "__cpp_lib_ranges_join_with",
    "category": "library",
    "macro_value": 0,
    "compiles": false,
    "status": "unsupported",
    "compile_time_ms": 391,
    "compiler": "/home/runner/.platformio/tools/toolchain-xtensa-esp-elf/bin/xtensa-esp32s3-elf-g++",
    "timestamp": "2026-04-12T02:34:44.338497",
    "error_output": "src/cpp23__ranges_join_with.cpp:10:137: error: 'join_with' is not a member of 'std::views'\n   10 | auto _test_cpp23__ranges_join_with() -> int { std::vector<std::vector<int>> v = {{1,2},{3,4}}; int s = 0; for (auto x : v | std::views::join_with(0)) s += x; return s == 10 ? 0 : 1; }\n      |                                                                                                                                         ^~~~~~~~~",
    "link_failure": false
  },
  {
    "platform": "esp32s3-arduino-v3",
    "platform_version": "55.03.36",
    "standard": "c++23",
    "feature": "cpp23/ranges_repeat",
    "macro": "__cpp_lib_ranges_repeat",
    "category": "library",
    "macro_value": 0,
    "compiles": false,
    "status": "unsupported",
    "compile_time_ms": 391,
    "compiler": "/home/runner/.platformio/tools/toolchain-xtensa-esp-elf/bin/xtensa-esp32s3-elf-g++",
    "timestamp": "2026-04-12T02:34:44.338501",
    "error_output": "src/cpp23__ranges_repeat.cpp:9:81: error: 'repeat' is not a member of 'std::views'\n    9 | auto _test_cpp23__ranges_repeat() -> int { int n = 0; for (auto x : std::views::repeat(42) | std::views::take(3)) n += x; return n == 126 ? 0 : 1; }\n      |                                                                                 ^~~~~~",
    "link_failure": false
  },
  {
    "platform": "esp32s3-arduino-v3",
    "platform_version": "55.03.36",
    "standard": "c++23",
    "feature": "cpp23/ranges_reserve_hint",
    "macro": "__cpp_lib_ranges_reserve_hint",
    "category": "library",
    "macro_value": 0,
    "compiles": true,
    "status": "unreported",
    "compile_time_ms": 391,
    "compiler": "/home/runner/.platformio/tools/toolchain-xtensa-esp-elf/bin/xtensa-esp32s3-elf-g++",
    "timestamp": "2026-04-12T02:34:44.338506",
    "error_output": null,
    "link_failure": false
  },
  {
    "platform": "esp32s3-arduino-v3",
    "platform_version": "55.03.36",
    "standard": "c++23",
    "feature": "cpp23/ranges_slide",
    "macro": "__cpp_lib_ranges_slide",
    "category": "library",
    "macro_value": 0,
    "compiles": false,
    "status": "unsupported",
    "compile_time_ms": 391,
    "compiler": "/home/runner/.platformio/tools/toolchain-xtensa-esp-elf/bin/xtensa-esp32s3-elf-g++",
    "timestamp": "2026-04-12T02:34:44.338510",
    "error_output": "src/cpp23__ranges_slide.cpp:10:111: error: 'slide' is not a member of 'std::views'\n   10 | auto _test_cpp23__ranges_slide() -> int { std::vector v = {1,2,3,4}; int n = 0; for (auto w : v | std::views::slide(2)) n++; return n == 3 ? 0 : 1; }\n      |                                                                                                               ^~~~~",
    "link_failure": false
  },
  {
    "platform": "esp32s3-arduino-v3",
    "platform_version": "55.03.36",
    "standard": "c++23",
    "feature": "cpp23/ranges_starts_ends_with",
    "macro": "__cpp_lib_ranges_starts_ends_with",
    "category": "library",
    "macro_value": 0,
    "compiles": false,
    "status": "unsupported",
    "compile_time_ms": 391,
    "compiler": "/home/runner/.platformio/tools/toolchain-xtensa-esp-elf/bin/xtensa-esp32s3-elf-g++",
    "timestamp": "2026-04-12T02:34:44.338514",
    "error_output": "src/cpp23__ranges_starts_ends_with.cpp:10:126: error: 'starts_with' is not a member of 'std::ranges'\n   10 | auto _test_cpp23__ranges_starts_ends_with() -> int { std::vector v = {1,2,3,4,5}; std::vector p = {1,2}; return std::ranges::starts_with(v, p) ? 0 : 1; }\n      |                                                                                                                              ^~~~~~~~~~~",
    "link_failure": false
  },
  {
    "platform": "esp32s3-arduino-v3",
    "platform_version": "55.03.36",
    "standard": "c++23",
    "feature": "cpp23/ranges_stride",
    "macro": "__cpp_lib_ranges_stride",
    "category": "library",
    "macro_value": 0,
    "compiles": false,
    "status": "unsupported",
    "compile_time_ms": 391,
    "compiler": "/home/runner/.platformio/tools/toolchain-xtensa-esp-elf/bin/xtensa-esp32s3-elf-g++",
    "timestamp": "2026-04-12T02:34:44.338518",
    "error_output": "src/cpp23__ranges_stride.cpp:10:116: error: 'stride' is not a member of 'std::views'\n   10 | auto _test_cpp23__ranges_stride() -> int { std::vector v = {1,2,3,4,5,6}; int s = 0; for (auto x : v | std::views::stride(2)) s += x; return s == 9 ? 0 : 1; }\n      |                                                                                                                    ^~~~~~",
    "link_failure": false
  },
  {
    "platform": "esp32s3-arduino-v3",
    "platform_version": "55.03.36",
    "standard": "c++23",
    "feature": "cpp23/ranges_to_container",
    "macro": "__cpp_lib_ranges_to_container",
    "category": "library",
    "macro_value": 0,
    "compiles": false,
    "status": "unsupported",
    "compile_time_ms": 391,
    "compiler": "/home/runner/.platformio/tools/toolchain-xtensa-esp-elf/bin/xtensa-esp32s3-elf-g++",
    "timestamp": "2026-04-12T02:34:44.338522",
    "error_output": "src/cpp23__ranges_to_container.cpp:10:97: error: 'to' is not a member of 'std::ranges'\n   10 | auto _test_cpp23__ranges_to_container() -> int { auto v = std::views::iota(1, 4) | std::ranges::to<std::vector>(); return v.size() == 3 && v[0] == 1 ? 0 : 1; }\n      |                                                                                                 ^~\nsrc/cpp23__ranges_to_container.cpp:10:111: error: missing template arguments before '>' token\n   10 | auto _test_cpp23__ranges_to_containe",
    "link_failure": false
  },
  {
    "platform": "esp32s3-arduino-v3",
    "platform_version": "55.03.36",
    "standard": "c++23",
    "feature": "cpp23/ranges_zip",
    "macro": "__cpp_lib_ranges_zip",
    "category": "library",
    "macro_value": 0,
    "compiles": false,
    "status": "unsupported",
    "compile_time_ms": 391,
    "compiler": "/home/runner/.platformio/tools/toolchain-xtensa-esp-elf/bin/xtensa-esp32s3-elf-g++",
    "timestamp": "2026-04-12T02:34:44.338526",
    "error_output": "src/cpp23__ranges_zip.cpp:10:132: error: 'zip' is not a member of 'std::views'\n   10 | auto _test_cpp23__ranges_zip() -> int { std::vector a = {1,2,3}; std::vector b = {4,5,6}; int s = 0; for (auto [x,y] : std::views::zip(a, b)) s += x + y; return s - 21; }\n      |                                                                                                                                    ^~~",
    "link_failure": false
  },
  {
    "platform": "esp32s3-arduino-v3",
    "platform_version": "55.03.36",
    "standard": "c++23",
    "feature": "cpp23/rcu",
    "macro": "__cpp_lib_rcu",
    "category": "library",
    "macro_value": 0,
    "compiles": false,
    "status": "unsupported",
    "compile_time_ms": 391,
    "compiler": "/home/runner/.platformio/tools/toolchain-xtensa-esp-elf/bin/xtensa-esp32s3-elf-g++",
    "timestamp": "2026-04-12T02:34:44.338530",
    "error_output": "src/cpp23__rcu.cpp:8:10: fatal error: rcu: No such file or directory\n    8 | #include <rcu>\n      |          ^~~~~",
    "link_failure": false
  },
  {
    "platform": "esp32s3-arduino-v3",
    "platform_version": "55.03.36",
    "standard": "c++23",
    "feature": "cpp23/reference_from_temporary",
    "macro": "__cpp_lib_reference_from_temporary",
    "category": "library",
    "macro_value": 0,
    "compiles": false,
    "status": "unsupported",
    "compile_time_ms": 391,
    "compiler": "/home/runner/.platformio/tools/toolchain-xtensa-esp-elf/bin/xtensa-esp32s3-elf-g++",
    "timestamp": "2026-04-12T02:34:44.338534",
    "error_output": "src/cpp23__reference_from_temporary.cpp:9:67: error: 'reference_constructs_from_temporary_v' is not a member of 'std'\n    9 | auto _test_cpp23__reference_from_temporary() -> int { return std::reference_constructs_from_temporary_v<const int&, int> ? 0 : 1; }\n      |                                                                   ^~~~~~~~~~~~~~~~~~~~~~~~~~~~~~~~~~~~~\nsrc/cpp23__reference_from_temporary.cpp:9:105: error: expected primary-expression before 'const'\n    9 | auto _test_cpp23__referen",
    "link_failure": false
  },
  {
    "platform": "esp32s3-arduino-v3",
    "platform_version": "55.03.36",
    "standard": "c++23",
    "feature": "cpp23/rtti",
    "macro": "__cpp_rtti",
    "category": "language",
    "macro_value": 0,
    "compiles": false,
    "status": "unsupported",
    "compile_time_ms": 391,
    "compiler": "/home/runner/.platformio/tools/toolchain-xtensa-esp-elf/bin/xtensa-esp32s3-elf-g++",
    "timestamp": "2026-04-12T02:34:44.338876",
    "error_output": "src/cpp23__rtti.cpp:11:73: error: cannot use 'typeid' with '-fno-rtti'\n   11 | auto _test_cpp23__rtti() -> int { Derived d; Base& b = d; return typeid(b) == typeid(Derived) ? 0 : 1; }\n      |                                                                         ^\nsrc/cpp23__rtti.cpp:11:93: error: cannot use 'typeid' with '-fno-rtti'\n   11 | auto _test_cpp23__rtti() -> int { Derived d; Base& b = d; return typeid(b) == typeid(Derived) ? 0 : 1; }\n      |                                           ",
    "link_failure": false
  },
  {
    "platform": "esp32s3-arduino-v3",
    "platform_version": "55.03.36",
    "standard": "c++23",
    "feature": "cpp23/senders",
    "macro": "__cpp_lib_senders",
    "category": "library",
    "macro_value": 0,
    "compiles": true,
    "status": "unreported",
    "compile_time_ms": 391,
    "compiler": "/home/runner/.platformio/tools/toolchain-xtensa-esp-elf/bin/xtensa-esp32s3-elf-g++",
    "timestamp": "2026-04-12T02:34:44.338881",
    "error_output": null,
    "link_failure": false
  },
  {
    "platform": "esp32s3-arduino-v3",
    "platform_version": "55.03.36",
    "standard": "c++23",
    "feature": "cpp23/simd_complex",
    "macro": "__cpp_lib_simd_complex",
    "category": "library",
    "macro_value": 0,
    "compiles": false,
    "status": "unsupported",
    "compile_time_ms": 391,
    "compiler": "/home/runner/.platformio/tools/toolchain-xtensa-esp-elf/bin/xtensa-esp32s3-elf-g++",
    "timestamp": "2026-04-12T02:34:44.338885",
    "error_output": "src/cpp23__simd_complex.cpp:8:10: fatal error: simd: No such file or directory\n    8 | #include <simd>\n      |          ^~~~~~",
    "link_failure": false
  },
  {
    "platform": "esp32s3-arduino-v3",
    "platform_version": "55.03.36",
    "standard": "c++23",
    "feature": "cpp23/simd_permutations",
    "macro": "__cpp_lib_simd_permutations",
    "category": "library",
    "macro_value": 0,
    "compiles": false,
    "status": "unsupported",
    "compile_time_ms": 391,
    "compiler": "/home/runner/.platformio/tools/toolchain-xtensa-esp-elf/bin/xtensa-esp32s3-elf-g++",
    "timestamp": "2026-04-12T02:34:44.338889",
    "error_output": "src/cpp23__simd_permutations.cpp:8:10: fatal error: simd: No such file or directory\n    8 | #include <simd>\n      |          ^~~~~~",
    "link_failure": false
  },
  {
    "platform": "esp32s3-arduino-v3",
    "platform_version": "55.03.36",
    "standard": "c++23",
    "feature": "cpp23/size_t_suffix",
    "macro": "__cpp_size_t_suffix",
    "category": "language",
    "macro_value": 0,
    "compiles": true,
    "status": "unreported",
    "compile_time_ms": 391,
    "compiler": "/home/runner/.platformio/tools/toolchain-xtensa-esp-elf/bin/xtensa-esp32s3-elf-g++",
    "timestamp": "2026-04-12T02:34:44.338893",
    "error_output": null,
    "link_failure": false
  },
  {
    "platform": "esp32s3-arduino-v3",
    "platform_version": "55.03.36",
    "standard": "c++23",
    "feature": "cpp23/spanstream",
    "macro": "__cpp_lib_spanstream",
    "category": "library",
    "macro_value": 0,
    "compiles": false,
    "status": "unsupported",
    "compile_time_ms": 391,
    "compiler": "/home/runner/.platformio/tools/toolchain-xtensa-esp-elf/bin/xtensa-esp32s3-elf-g++",
    "timestamp": "2026-04-12T02:34:44.338897",
    "error_output": "src/cpp23__spanstream.cpp:9:60: error: 'ospanstream' is not a member of 'std'\n    9 | auto _test_cpp23__spanstream() -> int { char buf[32]; std::ospanstream ss(buf); ss << 42; return 0; }\n      |                                                            ^~~~~~~~~~~\nsrc/cpp23__spanstream.cpp:9:81: error: 'ss' was not declared in this scope; did you mean 'SS'?\n    9 | auto _test_cpp23__spanstream() -> int { char buf[32]; std::ospanstream ss(buf); ss << 42; return 0; }\n      |                     ",
    "link_failure": false
  },
  {
    "platform": "esp32s3-arduino-v3",
    "platform_version": "55.03.36",
    "standard": "c++23",
    "feature": "cpp23/stacktrace",
    "macro": "__cpp_lib_stacktrace",
    "category": "library",
    "macro_value": 0,
    "compiles": false,
    "status": "unsupported",
    "compile_time_ms": 391,
    "compiler": "/home/runner/.platformio/tools/toolchain-xtensa-esp-elf/bin/xtensa-esp32s3-elf-g++",
    "timestamp": "2026-04-12T02:34:44.338901",
    "error_output": "src/cpp23__stacktrace.cpp:9:20: error: 'std::stacktrace' has not been declared\n    9 |     auto st = std::stacktrace::current();\n      |                    ^~~~~~~~~~",
    "link_failure": false
  },
  {
    "platform": "esp32s3-arduino-v3",
    "platform_version": "55.03.36",
    "standard": "c++23",
    "feature": "cpp23/start_lifetime_as",
    "macro": "__cpp_lib_start_lifetime_as",
    "category": "library",
    "macro_value": 0,
    "compiles": true,
    "status": "unreported",
    "compile_time_ms": 391,
    "compiler": "/home/runner/.platformio/tools/toolchain-xtensa-esp-elf/bin/xtensa-esp32s3-elf-g++",
    "timestamp": "2026-04-12T02:34:44.338906",
    "error_output": null,
    "link_failure": false
  },
  {
    "platform": "esp32s3-arduino-v3",
    "platform_version": "55.03.36",
    "standard": "c++23",
    "feature": "cpp23/static_call_operator",
    "macro": "__cpp_static_call_operator",
    "category": "language",
    "macro_value": 0,
    "compiles": true,
    "status": "unreported",
    "compile_time_ms": 391,
    "compiler": "/home/runner/.platformio/tools/toolchain-xtensa-esp-elf/bin/xtensa-esp32s3-elf-g++",
    "timestamp": "2026-04-12T02:34:44.338910",
    "error_output": null,
    "link_failure": false
  },
  {
    "platform": "esp32s3-arduino-v3",
    "platform_version": "55.03.36",
    "standard": "c++23",
    "feature": "cpp23/stdatomic_h",
    "macro": "__cpp_lib_stdatomic_h",
    "category": "library",
    "macro_value": 0,
    "compiles": false,
    "status": "unsupported",
    "compile_time_ms": 391,
    "compiler": "/home/runner/.platformio/tools/toolchain-xtensa-esp-elf/bin/xtensa-esp32s3-elf-g++",
    "timestamp": "2026-04-12T02:34:44.338914",
    "error_output": "src/cpp23__stdatomic_h.cpp:9:42: error: 'atomic_int' was not declared in this scope\n    9 | auto _test_cpp23__stdatomic_h() -> int { atomic_int a = 0; atomic_store(&a, 42); return atomic_load(&a) - 42; }\n      |                                          ^~~~~~~~~~\nsrc/cpp23__stdatomic_h.cpp:9:74: error: 'a' was not declared in this scope\n    9 | auto _test_cpp23__stdatomic_h() -> int { atomic_int a = 0; atomic_store(&a, 42); return atomic_load(&a) - 42; }\n      |                                  ",
    "link_failure": false
  },
  {
    "platform": "esp32s3-arduino-v3",
    "platform_version": "55.03.36",
    "standard": "c++23",
    "feature": "cpp23/string_contains",
    "macro": "__cpp_lib_string_contains",
    "category": "library",
    "macro_value": 0,
    "compiles": false,
    "status": "unsupported",
    "compile_time_ms": 391,
    "compiler": "/home/runner/.platformio/tools/toolchain-xtensa-esp-elf/bin/xtensa-esp32s3-elf-g++",
    "timestamp": "2026-04-12T02:34:44.338918",
    "error_output": "src/cpp23__string_contains.cpp:9:86: error: 'std::string' {aka 'class std::__cxx11::basic_string<char>'} has no member named 'contains'\n    9 | auto _test_cpp23__string_contains() -> int { std::string s = \"hello world\"; return s.contains(\"world\") ? 0 : 1; }\n      |                                                                                      ^~~~~~~~",
    "link_failure": false
  },
  {
    "platform": "esp32s3-arduino-v3",
    "platform_version": "55.03.36",
    "standard": "c++23",
    "feature": "cpp23/string_resize_and_overwrite",
    "macro": "__cpp_lib_string_resize_and_overwrite",
    "category": "library",
    "macro_value": 0,
    "compiles": false,
    "status": "unsupported",
    "compile_time_ms": 391,
    "compiler": "/home/runner/.platformio/tools/toolchain-xtensa-esp-elf/bin/xtensa-esp32s3-elf-g++",
    "timestamp": "2026-04-12T02:34:44.338922",
    "error_output": "src/cpp23__string_resize_and_overwrite.cpp:9:75: error: 'std::string' {aka 'class std::__cxx11::basic_string<char>'} has no member named 'resize_and_overwrite'; did you mean '__resize_and_overwrite'?\n    9 | auto _test_cpp23__string_resize_and_overwrite() -> int { std::string s; s.resize_and_overwrite(5, [](char* p, std::size_t n) { for (std::size_t i=0; i<n; ++i) p[i]='x'; return n; }); return s.size() == 5 ? 0 : 1; }\n      |                                                                      ",
    "link_failure": false
  },
  {
    "platform": "esp32s3-arduino-v3",
    "platform_version": "55.03.36",
    "standard": "c++23",
    "feature": "cpp23/task",
    "macro": "__cpp_lib_task",
    "category": "library",
    "macro_value": 0,
    "compiles": true,
    "status": "unreported",
    "compile_time_ms": 391,
    "compiler": "/home/runner/.platformio/tools/toolchain-xtensa-esp-elf/bin/xtensa-esp32s3-elf-g++",
    "timestamp": "2026-04-12T02:34:44.338926",
    "error_output": null,
    "link_failure": false
  },
  {
    "platform": "esp32s3-arduino-v3",
    "platform_version": "55.03.36",
    "standard": "c++23",
    "feature": "cpp23/template_parameters",
    "macro": "__cpp_template_parameters",
    "category": "language",
    "macro_value": 0,
    "compiles": true,
    "status": "unreported",
    "compile_time_ms": 391,
    "compiler": "/home/runner/.platformio/tools/toolchain-xtensa-esp-elf/bin/xtensa-esp32s3-elf-g++",
    "timestamp": "2026-04-12T02:34:44.338930",
    "error_output": null,
    "link_failure": false
  },
  {
    "platform": "esp32s3-arduino-v3",
    "platform_version": "55.03.36",
    "standard": "c++23",
    "feature": "cpp23/to_underlying",
    "macro": "__cpp_lib_to_underlying",
    "category": "library",
    "macro_value": 0,
    "compiles": false,
    "status": "unsupported",
    "compile_time_ms": 391,
    "compiler": "/home/runner/.platformio/tools/toolchain-xtensa-esp-elf/bin/xtensa-esp32s3-elf-g++",
    "timestamp": "2026-04-12T02:34:44.338934",
    "error_output": "src/cpp23__to_underlying.cpp:13:17: error: 'to_underlying' is not a member of 'std'\n   13 |     return std::to_underlying(Color::Green) - 2;\n      |                 ^~~~~~~~~~~~~",
    "link_failure": false
  },
  {
    "platform": "esp32s3-arduino-v3",
    "platform_version": "55.03.36",
    "standard": "c++23",
    "feature": "cpp23/trivial_union",
    "macro": "__cpp_trivial_union",
    "category": "language",
    "macro_value": 0,
    "compiles": true,
    "status": "unreported",
    "compile_time_ms": 391,
    "compiler": "/home/runner/.platformio/tools/toolchain-xtensa-esp-elf/bin/xtensa-esp32s3-elf-g++",
    "timestamp": "2026-04-12T02:34:44.338938",
    "error_output": null,
    "link_failure": false
  },
  {
    "platform": "esp32s3-arduino-v3",
    "platform_version": "55.03.36",
    "standard": "c++23",
    "feature": "cpp23/tuple_like",
    "macro": "__cpp_lib_tuple_like",
    "category": "library",
    "macro_value": 0,
    "compiles": true,
    "status": "unreported",
    "compile_time_ms": 391,
    "compiler": "/home/runner/.platformio/tools/toolchain-xtensa-esp-elf/bin/xtensa-esp32s3-elf-g++",
    "timestamp": "2026-04-12T02:34:44.338942",
    "error_output": null,
    "link_failure": false
  },
  {
    "platform": "esp32s3-arduino-v3",
    "platform_version": "55.03.36",
    "standard": "c++23",
    "feature": "cpp23/unreachable",
    "macro": "__cpp_lib_unreachable",
    "category": "library",
    "macro_value": 0,
    "compiles": false,
    "status": "unsupported",
    "compile_time_ms": 391,
    "compiler": "/home/runner/.platformio/tools/toolchain-xtensa-esp-elf/bin/xtensa-esp32s3-elf-g++",
    "timestamp": "2026-04-12T02:34:44.338945",
    "error_output": "src/cpp23__unreachable.cpp:9:80: error: 'unreachable' is not a member of 'std'\n    9 | auto _test_cpp23__unreachable() -> int { int x = 1; if (x == 1) return 0; std::unreachable(); }\n      |                                                                                ^~~~~~~~~~~\nsrc/cpp23__unreachable.cpp:9:95: error: control reaches end of non-void function [-Werror=return-type]\n    9 | auto _test_cpp23__unreachable() -> int { int x = 1; if (x == 1) return 0; std::unreachable(); }\n      |    ",
    "link_failure": false
  },
  {
    "platform": "esp32s3-arduino-v3",
    "platform_version": "55.03.36",
    "standard": "c++23",
    "feature": "cpp23/valarray_lib",
    "macro": "__cpp_lib_valarray",
    "category": "library",
    "macro_value": 0,
    "compiles": true,
    "status": "unreported",
    "compile_time_ms": 391,
    "compiler": "/home/runner/.platformio/tools/toolchain-xtensa-esp-elf/bin/xtensa-esp32s3-elf-g++",
    "timestamp": "2026-04-12T02:34:44.338949",
    "error_output": null,
    "link_failure": false
  }
]
